[
  {
    "id": 1169,
    "nomCarte": "Artifact Blast",
    "edition": "Antiquities",
    "langue": "English",
    "etat": "EX",
    "estimatedPrice": 1.4,
    "pricingModel": "standard_observed_condition_ratio",
    "marketAnchorPrice": 1.98,
    "ratioUsed": 0.7071,
    "confidence": 63,
    "observationCount": 1
  },
  {
    "id": 1170,
    "nomCarte": "Su-Chi",
    "edition": "Antiquities",
    "langue": "English",
    "etat": "EX",
    "estimatedPrice": 92,
    "pricingModel": "standard_observed_condition_ratio",
    "marketAnchorPrice": 94.19,
    "ratioUsed": 0.9767,
    "confidence": 63,
    "observationCount": 1
  },
  {
    "id": 1171,
    "nomCarte": "Su-Chi",
    "edition": "Antiquities",
    "langue": "English",
    "etat": "EX",
    "estimatedPrice": 92,
    "pricingModel": "standard_observed_condition_ratio",
    "marketAnchorPrice": 94.19,
    "ratioUsed": 0.9767,
    "confidence": 63,
    "observationCount": 1
  },
  {
    "id": 1172,
    "nomCarte": "Wall of Spears",
    "edition": "Antiquities",
    "langue": "English",
    "etat": "EX",
    "estimatedPrice": 2.28,
    "pricingModel": "standard_fallback_condition_ratio",
    "marketAnchorPrice": 2.2,
    "ratioUsed": 1.0341,
    "confidence": 35,
    "observationCount": 0
  },
  {
    "id": 1173,
    "nomCarte": "Desert",
    "edition": "Arabian Nights",
    "langue": "English",
    "etat": "EX",
    "estimatedPrice": 8.94,
    "pricingModel": "standard_observed_condition_ratio",
    "marketAnchorPrice": 10.98,
    "ratioUsed": 0.8142,
    "confidence": 63,
    "observationCount": 1
  },
  {
    "id": 1174,
    "nomCarte": "Desert",
    "edition": "Arabian Nights",
    "langue": "English",
    "etat": "NM",
    "estimatedPrice": 14.99,
    "pricingModel": "standard_observed_condition_ratio",
    "marketAnchorPrice": 10.98,
    "ratioUsed": 1.3652,
    "confidence": 63,
    "observationCount": 1
  },
  {
    "id": 1175,
    "nomCarte": "Desert",
    "edition": "Arabian Nights",
    "langue": "English",
    "etat": "EX",
    "estimatedPrice": 8.94,
    "pricingModel": "standard_observed_condition_ratio",
    "marketAnchorPrice": 10.98,
    "ratioUsed": 0.8142,
    "confidence": 63,
    "observationCount": 1
  },
  {
    "id": 1176,
    "nomCarte": "Desert Nomads",
    "edition": "Arabian Nights",
    "langue": "English",
    "etat": "EX",
    "estimatedPrice": 3.13,
    "pricingModel": "standard_observed_condition_ratio",
    "marketAnchorPrice": 4.11,
    "ratioUsed": 0.7616,
    "confidence": 63,
    "observationCount": 1
  },
  {
    "id": 1177,
    "nomCarte": "Erg Raiders (V.1)",
    "edition": "Arabian Nights",
    "langue": "English",
    "etat": "NM",
    "estimatedPrice": 4.75,
    "pricingModel": "standard_observed_condition_ratio",
    "marketAnchorPrice": 5.94,
    "ratioUsed": 0.7997,
    "confidence": 63,
    "observationCount": 1
  },
  {
    "id": 1178,
    "nomCarte": "Ghazbán Ogre",
    "edition": "Arabian Nights",
    "langue": "English",
    "etat": "EX",
    "estimatedPrice": 4.07,
    "pricingModel": "standard_fallback_condition_ratio",
    "marketAnchorPrice": 3.94,
    "ratioUsed": 1.0341,
    "confidence": 35,
    "observationCount": 0
  },
  {
    "id": 1179,
    "nomCarte": "Hasran Ogress (V.1)",
    "edition": "Arabian Nights",
    "langue": "English",
    "etat": "EX",
    "estimatedPrice": 3.2,
    "pricingModel": "standard_fallback_condition_ratio",
    "marketAnchorPrice": 3.09,
    "ratioUsed": 1.0341,
    "confidence": 35,
    "observationCount": 0
  },
  {
    "id": 1180,
    "nomCarte": "Hurr Jackal",
    "edition": "Arabian Nights",
    "langue": "English",
    "etat": "EX",
    "estimatedPrice": 3.72,
    "pricingModel": "standard_fallback_condition_ratio",
    "marketAnchorPrice": 3.6,
    "ratioUsed": 1.0341,
    "confidence": 35,
    "observationCount": 0
  },
  {
    "id": 1181,
    "nomCarte": "Moorish Cavalry (V.1)",
    "edition": "Arabian Nights",
    "langue": "English",
    "etat": "EX",
    "estimatedPrice": 4.13,
    "pricingModel": "standard_fallback_condition_ratio",
    "marketAnchorPrice": 3.99,
    "ratioUsed": 1.0341,
    "confidence": 35,
    "observationCount": 0
  },
  {
    "id": 1182,
    "nomCarte": "Nafs Asp (V.1)",
    "edition": "Arabian Nights",
    "langue": "English",
    "etat": "EX",
    "estimatedPrice": 11.3,
    "pricingModel": "standard_fallback_condition_ratio",
    "marketAnchorPrice": 10.93,
    "ratioUsed": 1.0341,
    "confidence": 35,
    "observationCount": 0
  },
  {
    "id": 1183,
    "nomCarte": "Piety (V.1)",
    "edition": "Arabian Nights",
    "langue": "English",
    "etat": "EX",
    "estimatedPrice": 5.63,
    "pricingModel": "standard_fallback_condition_ratio",
    "marketAnchorPrice": 5.44,
    "ratioUsed": 1.0341,
    "confidence": 35,
    "observationCount": 0
  },
  {
    "id": 1184,
    "nomCarte": "Sandstorm",
    "edition": "Arabian Nights",
    "langue": "English",
    "etat": "EX",
    "estimatedPrice": 3.23,
    "pricingModel": "standard_fallback_condition_ratio",
    "marketAnchorPrice": 3.12,
    "ratioUsed": 1.0341,
    "confidence": 35,
    "observationCount": 0
  },
  {
    "id": 1185,
    "nomCarte": "War Elephant (V.1)",
    "edition": "Arabian Nights",
    "langue": "English",
    "etat": "EX",
    "estimatedPrice": 6.39,
    "pricingModel": "standard_fallback_condition_ratio",
    "marketAnchorPrice": 6.18,
    "ratioUsed": 1.0341,
    "confidence": 35,
    "observationCount": 0
  },
  {
    "id": 1186,
    "nomCarte": "War Elephant (V.2)",
    "edition": "Arabian Nights",
    "langue": "English",
    "etat": "EX",
    "estimatedPrice": 9.94,
    "pricingModel": "standard_observed_condition_ratio",
    "marketAnchorPrice": 6.18,
    "ratioUsed": 1.6084,
    "confidence": 71,
    "observationCount": 2
  },
  {
    "id": 1187,
    "nomCarte": "Wyluli Wolf (V.2)",
    "edition": "Arabian Nights",
    "langue": "English",
    "etat": "EX",
    "estimatedPrice": 13.17,
    "pricingModel": "standard_fallback_condition_ratio",
    "marketAnchorPrice": 12.74,
    "ratioUsed": 1.0341,
    "confidence": 35,
    "observationCount": 0
  },
  {
    "id": 1188,
    "nomCarte": "Hymn to Tourach (V.1)",
    "edition": "Fallen Empires",
    "langue": "English",
    "etat": "NM",
    "estimatedPrice": 1.35,
    "pricingModel": "standard_fallback_condition_ratio",
    "marketAnchorPrice": 0.86,
    "ratioUsed": 1.5743,
    "confidence": 35,
    "observationCount": 0
  },
  {
    "id": 1189,
    "nomCarte": "Hymn to Tourach (V.2)",
    "edition": "Fallen Empires",
    "langue": "English",
    "etat": "EX",
    "estimatedPrice": 1,
    "pricingModel": "standard_fallback_condition_ratio",
    "marketAnchorPrice": 0.97,
    "ratioUsed": 1.0341,
    "confidence": 35,
    "observationCount": 0
  },
  {
    "id": 1190,
    "nomCarte": "Hymn to Tourach (V.3)",
    "edition": "Fallen Empires",
    "langue": "English",
    "etat": "NM",
    "estimatedPrice": 1.51,
    "pricingModel": "standard_fallback_condition_ratio",
    "marketAnchorPrice": 0.96,
    "ratioUsed": 1.5743,
    "confidence": 35,
    "observationCount": 0
  },
  {
    "id": 1191,
    "nomCarte": "Black Knight",
    "edition": "Foreign Black Bordered",
    "langue": "French",
    "etat": "EX",
    "estimatedPrice": 3.89,
    "pricingModel": "standard_fallback_condition_ratio",
    "marketAnchorPrice": 3.76,
    "ratioUsed": 1.0341,
    "confidence": 35,
    "observationCount": 0
  },
  {
    "id": 1192,
    "nomCarte": "Black Knight",
    "edition": "Foreign Black Bordered",
    "langue": "French",
    "etat": "EX",
    "estimatedPrice": 3.89,
    "pricingModel": "standard_fallback_condition_ratio",
    "marketAnchorPrice": 3.76,
    "ratioUsed": 1.0341,
    "confidence": 35,
    "observationCount": 0
  },
  {
    "id": 1193,
    "nomCarte": "Black Knight",
    "edition": "Foreign Black Bordered",
    "langue": "French",
    "etat": "NM",
    "estimatedPrice": 5.92,
    "pricingModel": "standard_fallback_condition_ratio",
    "marketAnchorPrice": 3.76,
    "ratioUsed": 1.5743,
    "confidence": 35,
    "observationCount": 0
  },
  {
    "id": 1194,
    "nomCarte": "Black Knight",
    "edition": "Foreign Black Bordered",
    "langue": "French",
    "etat": "EX",
    "estimatedPrice": 3.89,
    "pricingModel": "standard_fallback_condition_ratio",
    "marketAnchorPrice": 3.76,
    "ratioUsed": 1.0341,
    "confidence": 35,
    "observationCount": 0
  },
  {
    "id": 1195,
    "nomCarte": "Black Vise",
    "edition": "Foreign Black Bordered",
    "langue": "French",
    "etat": "PL",
    "estimatedPrice": 3.49,
    "pricingModel": "standard_observed_condition_ratio",
    "marketAnchorPrice": 12.74,
    "ratioUsed": 0.2739,
    "confidence": 63,
    "observationCount": 1
  },
  {
    "id": 1196,
    "nomCarte": "Channel",
    "edition": "Foreign Black Bordered",
    "langue": "French",
    "etat": "EX",
    "estimatedPrice": 0.98,
    "pricingModel": "standard_fallback_condition_ratio",
    "marketAnchorPrice": 0.95,
    "ratioUsed": 1.0341,
    "confidence": 35,
    "observationCount": 0
  },
  {
    "id": 1197,
    "nomCarte": "Dark Ritual",
    "edition": "Foreign Black Bordered",
    "langue": "French",
    "etat": "EX",
    "estimatedPrice": 5.7,
    "pricingModel": "standard_fallback_condition_ratio",
    "marketAnchorPrice": 5.51,
    "ratioUsed": 1.0341,
    "confidence": 35,
    "observationCount": 0
  },
  {
    "id": 1198,
    "nomCarte": "Dark Ritual",
    "edition": "Foreign Black Bordered",
    "langue": "French",
    "etat": "NM",
    "estimatedPrice": 8.67,
    "pricingModel": "standard_fallback_condition_ratio",
    "marketAnchorPrice": 5.51,
    "ratioUsed": 1.5743,
    "confidence": 35,
    "observationCount": 0
  },
  {
    "id": 1199,
    "nomCarte": "Disenchant",
    "edition": "Foreign Black Bordered",
    "langue": "French",
    "etat": "EX",
    "estimatedPrice": 0.95,
    "pricingModel": "standard_fallback_condition_ratio",
    "marketAnchorPrice": 0.92,
    "ratioUsed": 1.0341,
    "confidence": 35,
    "observationCount": 0
  },
  {
    "id": 1200,
    "nomCarte": "Gloom",
    "edition": "Foreign Black Bordered",
    "langue": "French",
    "etat": "NM",
    "estimatedPrice": 21.32,
    "pricingModel": "standard_fallback_condition_ratio",
    "marketAnchorPrice": 13.54,
    "ratioUsed": 1.5743,
    "confidence": 35,
    "observationCount": 0
  },
  {
    "id": 1201,
    "nomCarte": "Gloom",
    "edition": "Foreign Black Bordered",
    "langue": "French",
    "etat": "EX",
    "estimatedPrice": 14,
    "pricingModel": "standard_fallback_condition_ratio",
    "marketAnchorPrice": 13.54,
    "ratioUsed": 1.0341,
    "confidence": 35,
    "observationCount": 0
  },
  {
    "id": 1202,
    "nomCarte": "Gloom",
    "edition": "Foreign Black Bordered",
    "langue": "French",
    "etat": "EX",
    "estimatedPrice": 14,
    "pricingModel": "standard_fallback_condition_ratio",
    "marketAnchorPrice": 13.54,
    "ratioUsed": 1.0341,
    "confidence": 35,
    "observationCount": 0
  },
  {
    "id": 1203,
    "nomCarte": "Gloom",
    "edition": "Foreign Black Bordered",
    "langue": "French",
    "etat": "EX",
    "estimatedPrice": 14,
    "pricingModel": "standard_fallback_condition_ratio",
    "marketAnchorPrice": 13.54,
    "ratioUsed": 1.0341,
    "confidence": 35,
    "observationCount": 0
  },
  {
    "id": 1204,
    "nomCarte": "Island (V.1)",
    "edition": "Foreign Black Bordered",
    "langue": "French",
    "etat": "EX",
    "estimatedPrice": 0,
    "pricingModel": "standard_fallback_condition_ratio",
    "marketAnchorPrice": 0,
    "ratioUsed": 1.0341,
    "confidence": 0,
    "observationCount": 0
  },
  {
    "id": 1205,
    "nomCarte": "Juggernaut",
    "edition": "Foreign Black Bordered",
    "langue": "French",
    "etat": "EX",
    "estimatedPrice": 3.15,
    "pricingModel": "standard_fallback_condition_ratio",
    "marketAnchorPrice": 3.05,
    "ratioUsed": 1.0341,
    "confidence": 35,
    "observationCount": 0
  },
  {
    "id": 1206,
    "nomCarte": "Juggernaut",
    "edition": "Foreign Black Bordered",
    "langue": "French",
    "etat": "EX",
    "estimatedPrice": 3.15,
    "pricingModel": "standard_fallback_condition_ratio",
    "marketAnchorPrice": 3.05,
    "ratioUsed": 1.0341,
    "confidence": 35,
    "observationCount": 0
  },
  {
    "id": 1207,
    "nomCarte": "Juggernaut",
    "edition": "Foreign Black Bordered",
    "langue": "French",
    "etat": "EX",
    "estimatedPrice": 3.15,
    "pricingModel": "standard_fallback_condition_ratio",
    "marketAnchorPrice": 3.05,
    "ratioUsed": 1.0341,
    "confidence": 35,
    "observationCount": 0
  },
  {
    "id": 1208,
    "nomCarte": "Juggernaut",
    "edition": "Foreign Black Bordered",
    "langue": "French",
    "etat": "EX",
    "estimatedPrice": 3.15,
    "pricingModel": "standard_fallback_condition_ratio",
    "marketAnchorPrice": 3.05,
    "ratioUsed": 1.0341,
    "confidence": 35,
    "observationCount": 0
  },
  {
    "id": 1209,
    "nomCarte": "Lightning Bolt",
    "edition": "Foreign Black Bordered",
    "langue": "French",
    "etat": "PO",
    "estimatedPrice": 9.21,
    "pricingModel": "standard_fallback_condition_ratio",
    "marketAnchorPrice": 12.76,
    "ratioUsed": 0.7215,
    "confidence": 35,
    "observationCount": 0
  },
  {
    "id": 1210,
    "nomCarte": "Birds of Paradise",
    "edition": "Foreign White Bordered",
    "langue": "French",
    "etat": "EX",
    "estimatedPrice": 13.99,
    "pricingModel": "standard_observed_condition_ratio",
    "marketAnchorPrice": 18.37,
    "ratioUsed": 0.7616,
    "confidence": 63,
    "observationCount": 1
  },
  {
    "id": 1211,
    "nomCarte": "Birds of Paradise",
    "edition": "Foreign White Bordered",
    "langue": "French",
    "etat": "GD",
    "estimatedPrice": 8,
    "pricingModel": "standard_observed_condition_ratio",
    "marketAnchorPrice": 18.37,
    "ratioUsed": 0.4355,
    "confidence": 63,
    "observationCount": 1
  },
  {
    "id": 1212,
    "nomCarte": "Birds of Paradise",
    "edition": "Foreign White Bordered",
    "langue": "French",
    "etat": "GD",
    "estimatedPrice": 8,
    "pricingModel": "standard_observed_condition_ratio",
    "marketAnchorPrice": 18.37,
    "ratioUsed": 0.4355,
    "confidence": 63,
    "observationCount": 1
  },
  {
    "id": 1213,
    "nomCarte": "Birds of Paradise",
    "edition": "Foreign White Bordered",
    "langue": "French",
    "etat": "GD",
    "estimatedPrice": 8,
    "pricingModel": "standard_observed_condition_ratio",
    "marketAnchorPrice": 18.37,
    "ratioUsed": 0.4355,
    "confidence": 63,
    "observationCount": 1
  },
  {
    "id": 1214,
    "nomCarte": "Blue Elemental Blast",
    "edition": "Foreign White Bordered",
    "langue": "French",
    "etat": "EX",
    "estimatedPrice": 2.32,
    "pricingModel": "standard_fallback_condition_ratio",
    "marketAnchorPrice": 2.24,
    "ratioUsed": 1.0341,
    "confidence": 35,
    "observationCount": 0
  },
  {
    "id": 1215,
    "nomCarte": "Dark Ritual",
    "edition": "Foreign White Bordered",
    "langue": "French",
    "etat": "EX",
    "estimatedPrice": 2.18,
    "pricingModel": "standard_fallback_condition_ratio",
    "marketAnchorPrice": 2.11,
    "ratioUsed": 1.0341,
    "confidence": 35,
    "observationCount": 0
  },
  {
    "id": 1216,
    "nomCarte": "Dark Ritual",
    "edition": "Foreign White Bordered",
    "langue": "French",
    "etat": "EX",
    "estimatedPrice": 2.18,
    "pricingModel": "standard_fallback_condition_ratio",
    "marketAnchorPrice": 2.11,
    "ratioUsed": 1.0341,
    "confidence": 35,
    "observationCount": 0
  },
  {
    "id": 1217,
    "nomCarte": "Dark Ritual",
    "edition": "Foreign White Bordered",
    "langue": "French",
    "etat": "EX",
    "estimatedPrice": 2.18,
    "pricingModel": "standard_fallback_condition_ratio",
    "marketAnchorPrice": 2.11,
    "ratioUsed": 1.0341,
    "confidence": 35,
    "observationCount": 0
  },
  {
    "id": 1218,
    "nomCarte": "Elvish Archers",
    "edition": "Foreign White Bordered",
    "langue": "French",
    "etat": "EX",
    "estimatedPrice": 2.31,
    "pricingModel": "standard_fallback_condition_ratio",
    "marketAnchorPrice": 2.23,
    "ratioUsed": 1.0341,
    "confidence": 35,
    "observationCount": 0
  },
  {
    "id": 1219,
    "nomCarte": "Hypnotic Specter",
    "edition": "Foreign White Bordered",
    "langue": "French",
    "etat": "EX",
    "estimatedPrice": 5.05,
    "pricingModel": "standard_fallback_condition_ratio",
    "marketAnchorPrice": 4.88,
    "ratioUsed": 1.0341,
    "confidence": 35,
    "observationCount": 0
  },
  {
    "id": 1220,
    "nomCarte": "Hypnotic Specter",
    "edition": "Foreign White Bordered",
    "langue": "French",
    "etat": "GD",
    "estimatedPrice": 4.11,
    "pricingModel": "standard_fallback_condition_ratio",
    "marketAnchorPrice": 4.88,
    "ratioUsed": 0.8431,
    "confidence": 35,
    "observationCount": 0
  },
  {
    "id": 1221,
    "nomCarte": "Hypnotic Specter",
    "edition": "Foreign White Bordered",
    "langue": "French",
    "etat": "GD",
    "estimatedPrice": 4.11,
    "pricingModel": "standard_fallback_condition_ratio",
    "marketAnchorPrice": 4.88,
    "ratioUsed": 0.8431,
    "confidence": 35,
    "observationCount": 0
  },
  {
    "id": 1222,
    "nomCarte": "Hypnotic Specter",
    "edition": "Foreign White Bordered",
    "langue": "French",
    "etat": "EX",
    "estimatedPrice": 5.05,
    "pricingModel": "standard_fallback_condition_ratio",
    "marketAnchorPrice": 4.88,
    "ratioUsed": 1.0341,
    "confidence": 35,
    "observationCount": 0
  },
  {
    "id": 1223,
    "nomCarte": "Hypnotic Specter",
    "edition": "Foreign White Bordered",
    "langue": "French",
    "etat": "EX",
    "estimatedPrice": 5.05,
    "pricingModel": "standard_fallback_condition_ratio",
    "marketAnchorPrice": 4.88,
    "ratioUsed": 1.0341,
    "confidence": 35,
    "observationCount": 0
  },
  {
    "id": 1224,
    "nomCarte": "Hypnotic Specter",
    "edition": "Foreign White Bordered",
    "langue": "French",
    "etat": "EX",
    "estimatedPrice": 5.05,
    "pricingModel": "standard_fallback_condition_ratio",
    "marketAnchorPrice": 4.88,
    "ratioUsed": 1.0341,
    "confidence": 35,
    "observationCount": 0
  },
  {
    "id": 1225,
    "nomCarte": "Lightning Bolt",
    "edition": "Foreign White Bordered",
    "langue": "French",
    "etat": "EX",
    "estimatedPrice": 1.87,
    "pricingModel": "standard_fallback_condition_ratio",
    "marketAnchorPrice": 1.81,
    "ratioUsed": 1.0341,
    "confidence": 35,
    "observationCount": 0
  },
  {
    "id": 1226,
    "nomCarte": "Lightning Bolt",
    "edition": "Foreign White Bordered",
    "langue": "French",
    "etat": "EX",
    "estimatedPrice": 1.87,
    "pricingModel": "standard_fallback_condition_ratio",
    "marketAnchorPrice": 1.81,
    "ratioUsed": 1.0341,
    "confidence": 35,
    "observationCount": 0
  },
  {
    "id": 1227,
    "nomCarte": "Lord of the Pit",
    "edition": "Foreign White Bordered",
    "langue": "French",
    "etat": "EX",
    "estimatedPrice": 0.8,
    "pricingModel": "standard_observed_condition_ratio",
    "marketAnchorPrice": 1.8,
    "ratioUsed": 0.4444,
    "confidence": 63,
    "observationCount": 1
  },
  {
    "id": 1228,
    "nomCarte": "Meekstone",
    "edition": "Foreign White Bordered",
    "langue": "French",
    "etat": "NM",
    "estimatedPrice": 8.99,
    "pricingModel": "standard_observed_condition_ratio",
    "marketAnchorPrice": 8.47,
    "ratioUsed": 1.0614,
    "confidence": 63,
    "observationCount": 1
  },
  {
    "id": 1229,
    "nomCarte": "Meekstone",
    "edition": "Foreign White Bordered",
    "langue": "French",
    "etat": "EX",
    "estimatedPrice": 4.49,
    "pricingModel": "standard_observed_condition_ratio",
    "marketAnchorPrice": 8.47,
    "ratioUsed": 0.5301,
    "confidence": 63,
    "observationCount": 1
  },
  {
    "id": 1230,
    "nomCarte": "Mind Twist",
    "edition": "Foreign White Bordered",
    "langue": "French",
    "etat": "EX",
    "estimatedPrice": 5.67,
    "pricingModel": "standard_fallback_condition_ratio",
    "marketAnchorPrice": 5.48,
    "ratioUsed": 1.0341,
    "confidence": 35,
    "observationCount": 0
  },
  {
    "id": 1231,
    "nomCarte": "Nevinyrral's Disk",
    "edition": "Foreign White Bordered",
    "langue": "French",
    "etat": "NM",
    "estimatedPrice": 8.99,
    "pricingModel": "standard_observed_condition_ratio",
    "marketAnchorPrice": 5.94,
    "ratioUsed": 1.5135,
    "confidence": 63,
    "observationCount": 1
  },
  {
    "id": 1232,
    "nomCarte": "Nevinyrral's Disk",
    "edition": "Foreign White Bordered",
    "langue": "French",
    "etat": "EX",
    "estimatedPrice": 4,
    "pricingModel": "standard_observed_condition_ratio",
    "marketAnchorPrice": 5.94,
    "ratioUsed": 0.6734,
    "confidence": 63,
    "observationCount": 1
  },
  {
    "id": 1233,
    "nomCarte": "Red Elemental Blast",
    "edition": "Foreign White Bordered",
    "langue": "French",
    "etat": "EX",
    "estimatedPrice": 4,
    "pricingModel": "standard_observed_condition_ratio",
    "marketAnchorPrice": 5.89,
    "ratioUsed": 0.6791,
    "confidence": 63,
    "observationCount": 1
  },
  {
    "id": 1234,
    "nomCarte": "Savannah Lions",
    "edition": "Foreign White Bordered",
    "langue": "French",
    "etat": "EX",
    "estimatedPrice": 6.7,
    "pricingModel": "standard_fallback_condition_ratio",
    "marketAnchorPrice": 6.48,
    "ratioUsed": 1.0341,
    "confidence": 35,
    "observationCount": 0
  },
  {
    "id": 1235,
    "nomCarte": "Serra Angel",
    "edition": "Foreign White Bordered",
    "langue": "French",
    "etat": "EX",
    "estimatedPrice": 0.5,
    "pricingModel": "standard_observed_condition_ratio",
    "marketAnchorPrice": 2.39,
    "ratioUsed": 0.2092,
    "confidence": 63,
    "observationCount": 1
  },
  {
    "id": 1236,
    "nomCarte": "Sol Ring",
    "edition": "Foreign White Bordered",
    "langue": "French",
    "etat": "EX",
    "estimatedPrice": 9,
    "pricingModel": "standard_observed_condition_ratio",
    "marketAnchorPrice": 9.44,
    "ratioUsed": 0.9534,
    "confidence": 63,
    "observationCount": 1
  },
  {
    "id": 1237,
    "nomCarte": "Sol Ring",
    "edition": "Foreign White Bordered",
    "langue": "French",
    "etat": "NM",
    "estimatedPrice": 16,
    "pricingModel": "standard_observed_condition_ratio",
    "marketAnchorPrice": 9.44,
    "ratioUsed": 1.6949,
    "confidence": 63,
    "observationCount": 1
  },
  {
    "id": 1238,
    "nomCarte": "Sol Ring",
    "edition": "Foreign White Bordered",
    "langue": "Italian",
    "etat": "GD",
    "estimatedPrice": 5.5,
    "pricingModel": "standard_observed_condition_ratio",
    "marketAnchorPrice": 9.44,
    "ratioUsed": 0.5826,
    "confidence": 63,
    "observationCount": 1
  },
  {
    "id": 1239,
    "nomCarte": "Sol Ring",
    "edition": "Foreign White Bordered",
    "langue": "French",
    "etat": "EX",
    "estimatedPrice": 9,
    "pricingModel": "standard_observed_condition_ratio",
    "marketAnchorPrice": 9.44,
    "ratioUsed": 0.9534,
    "confidence": 63,
    "observationCount": 1
  },
  {
    "id": 1240,
    "nomCarte": "Sorceress Queen",
    "edition": "Foreign White Bordered",
    "langue": "French",
    "etat": "EX",
    "estimatedPrice": 1.8,
    "pricingModel": "standard_observed_condition_ratio",
    "marketAnchorPrice": 3.02,
    "ratioUsed": 0.596,
    "confidence": 63,
    "observationCount": 1
  },
  {
    "id": 1241,
    "nomCarte": "The Rack",
    "edition": "Foreign White Bordered",
    "langue": "French",
    "etat": "EX",
    "estimatedPrice": 1.44,
    "pricingModel": "standard_fallback_condition_ratio",
    "marketAnchorPrice": 1.39,
    "ratioUsed": 1.0341,
    "confidence": 35,
    "observationCount": 0
  },
  {
    "id": 1242,
    "nomCarte": "The Rack",
    "edition": "Foreign White Bordered",
    "langue": "French",
    "etat": "GD",
    "estimatedPrice": 1.17,
    "pricingModel": "standard_fallback_condition_ratio",
    "marketAnchorPrice": 1.39,
    "ratioUsed": 0.8431,
    "confidence": 35,
    "observationCount": 0
  },
  {
    "id": 1243,
    "nomCarte": "The Rack",
    "edition": "Foreign White Bordered",
    "langue": "French",
    "etat": "EX",
    "estimatedPrice": 1.44,
    "pricingModel": "standard_fallback_condition_ratio",
    "marketAnchorPrice": 1.39,
    "ratioUsed": 1.0341,
    "confidence": 35,
    "observationCount": 0
  },
  {
    "id": 1244,
    "nomCarte": "The Rack",
    "edition": "Foreign White Bordered",
    "langue": "French",
    "etat": "EX",
    "estimatedPrice": 1.44,
    "pricingModel": "standard_fallback_condition_ratio",
    "marketAnchorPrice": 1.39,
    "ratioUsed": 1.0341,
    "confidence": 35,
    "observationCount": 0
  },
  {
    "id": 1245,
    "nomCarte": "Verduran Enchantress",
    "edition": "Foreign White Bordered",
    "langue": "French",
    "etat": "NM",
    "estimatedPrice": 3.97,
    "pricingModel": "standard_fallback_condition_ratio",
    "marketAnchorPrice": 2.52,
    "ratioUsed": 1.5743,
    "confidence": 35,
    "observationCount": 0
  },
  {
    "id": 1246,
    "nomCarte": "Hypnotic Specter",
    "edition": "Fourth Edition",
    "langue": "English",
    "etat": "GD",
    "estimatedPrice": 4.85,
    "pricingModel": "standard_fallback_condition_ratio",
    "marketAnchorPrice": 5.75,
    "ratioUsed": 0.8431,
    "confidence": 35,
    "observationCount": 0
  },
  {
    "id": 1247,
    "nomCarte": "Royal Assassin",
    "edition": "Fourth Edition",
    "langue": "French",
    "etat": "NM",
    "estimatedPrice": 7.9,
    "pricingModel": "standard_observed_condition_ratio",
    "marketAnchorPrice": 2.08,
    "ratioUsed": 3.7981,
    "confidence": 63,
    "observationCount": 1
  },
  {
    "id": 1248,
    "nomCarte": "Avoid Fate",
    "edition": "Legends",
    "langue": "English",
    "etat": "EX",
    "estimatedPrice": 8,
    "pricingModel": "standard_fallback_condition_ratio",
    "marketAnchorPrice": 7.74,
    "ratioUsed": 1.0341,
    "confidence": 35,
    "observationCount": 0
  },
  {
    "id": 1249,
    "nomCarte": "Avoid Fate",
    "edition": "Legends",
    "langue": "English",
    "etat": "EX",
    "estimatedPrice": 8,
    "pricingModel": "standard_fallback_condition_ratio",
    "marketAnchorPrice": 7.74,
    "ratioUsed": 1.0341,
    "confidence": 35,
    "observationCount": 0
  },
  {
    "id": 1250,
    "nomCarte": "Avoid Fate",
    "edition": "Legends",
    "langue": "English",
    "etat": "EX",
    "estimatedPrice": 8,
    "pricingModel": "standard_fallback_condition_ratio",
    "marketAnchorPrice": 7.74,
    "ratioUsed": 1.0341,
    "confidence": 35,
    "observationCount": 0
  },
  {
    "id": 1251,
    "nomCarte": "Relic Bind",
    "edition": "Legends",
    "langue": "English",
    "etat": "EX",
    "estimatedPrice": 1.73,
    "pricingModel": "standard_fallback_condition_ratio",
    "marketAnchorPrice": 1.67,
    "ratioUsed": 1.0341,
    "confidence": 35,
    "observationCount": 0
  },
  {
    "id": 1252,
    "nomCarte": "Righteous Avengers",
    "edition": "Legends",
    "langue": "English",
    "etat": "EX",
    "estimatedPrice": 2.06,
    "pricingModel": "standard_fallback_condition_ratio",
    "marketAnchorPrice": 1.99,
    "ratioUsed": 1.0341,
    "confidence": 35,
    "observationCount": 0
  },
  {
    "id": 1253,
    "nomCarte": "Seeker",
    "edition": "Legends",
    "langue": "English",
    "etat": "EX",
    "estimatedPrice": 1.34,
    "pricingModel": "standard_fallback_condition_ratio",
    "marketAnchorPrice": 1.3,
    "ratioUsed": 1.0341,
    "confidence": 35,
    "observationCount": 0
  },
  {
    "id": 1254,
    "nomCarte": "Undertow",
    "edition": "Legends",
    "langue": "English",
    "etat": "EX",
    "estimatedPrice": 1.94,
    "pricingModel": "standard_fallback_condition_ratio",
    "marketAnchorPrice": 1.88,
    "ratioUsed": 1.0341,
    "confidence": 35,
    "observationCount": 0
  },
  {
    "id": 1255,
    "nomCarte": "Underworld Dreams",
    "edition": "Legends",
    "langue": "English",
    "etat": "EX",
    "estimatedPrice": 88.66,
    "pricingModel": "standard_observed_condition_ratio",
    "marketAnchorPrice": 83.03,
    "ratioUsed": 1.0678,
    "confidence": 63,
    "observationCount": 1
  },
  {
    "id": 1256,
    "nomCarte": "Underworld Dreams",
    "edition": "Legends",
    "langue": "English",
    "etat": "EX",
    "estimatedPrice": 88.66,
    "pricingModel": "standard_observed_condition_ratio",
    "marketAnchorPrice": 83.03,
    "ratioUsed": 1.0678,
    "confidence": 63,
    "observationCount": 1
  },
  {
    "id": 1257,
    "nomCarte": "Underworld Dreams",
    "edition": "Legends",
    "langue": "English",
    "etat": "EX",
    "estimatedPrice": 88.66,
    "pricingModel": "standard_observed_condition_ratio",
    "marketAnchorPrice": 83.03,
    "ratioUsed": 1.0678,
    "confidence": 63,
    "observationCount": 1
  },
  {
    "id": 1258,
    "nomCarte": "Underworld Dreams",
    "edition": "Legends",
    "langue": "English",
    "etat": "GD",
    "estimatedPrice": 78.18,
    "pricingModel": "standard_observed_condition_ratio",
    "marketAnchorPrice": 83.03,
    "ratioUsed": 0.9416,
    "confidence": 63,
    "observationCount": 1
  },
  {
    "id": 1259,
    "nomCarte": "Urborg",
    "edition": "Legends",
    "langue": "English",
    "etat": "EX",
    "estimatedPrice": 19.85,
    "pricingModel": "standard_fallback_condition_ratio",
    "marketAnchorPrice": 19.2,
    "ratioUsed": 1.0341,
    "confidence": 35,
    "observationCount": 0
  },
  {
    "id": 1260,
    "nomCarte": "Walking Dead",
    "edition": "Legends",
    "langue": "English",
    "etat": "EX",
    "estimatedPrice": 1,
    "pricingModel": "standard_observed_condition_ratio",
    "marketAnchorPrice": 1.95,
    "ratioUsed": 0.5128,
    "confidence": 63,
    "observationCount": 1
  },
  {
    "id": 1261,
    "nomCarte": "Wall of Dust",
    "edition": "Legends",
    "langue": "English",
    "etat": "EX",
    "estimatedPrice": 1.29,
    "pricingModel": "standard_observed_condition_ratio",
    "marketAnchorPrice": 1.67,
    "ratioUsed": 0.7725,
    "confidence": 63,
    "observationCount": 1
  },
  {
    "id": 1262,
    "nomCarte": "Vaevictis Asmadi",
    "edition": "Legends Italian",
    "langue": "Italian",
    "etat": "EX",
    "estimatedPrice": 29.96,
    "pricingModel": "standard_fallback_condition_ratio",
    "marketAnchorPrice": 28.97,
    "ratioUsed": 1.0341,
    "confidence": 35,
    "observationCount": 0
  },
  {
    "id": 1263,
    "nomCarte": "Mishra's Factory",
    "edition": "Renaissance",
    "langue": "French",
    "etat": "EX",
    "estimatedPrice": 9,
    "pricingModel": "standard_observed_condition_ratio",
    "marketAnchorPrice": 9.83,
    "ratioUsed": 0.9156,
    "confidence": 63,
    "observationCount": 1
  },
  {
    "id": 1264,
    "nomCarte": "Strip Mine",
    "edition": "Renaissance",
    "langue": "French",
    "etat": "EX",
    "estimatedPrice": 5.49,
    "pricingModel": "standard_observed_condition_ratio",
    "marketAnchorPrice": 6.28,
    "ratioUsed": 0.8742,
    "confidence": 63,
    "observationCount": 1
  },
  {
    "id": 1265,
    "nomCarte": "Armageddon",
    "edition": "Revised",
    "langue": "English",
    "etat": "EX",
    "estimatedPrice": 10,
    "pricingModel": "standard_observed_condition_ratio",
    "marketAnchorPrice": 12.89,
    "ratioUsed": 0.7758,
    "confidence": 63,
    "observationCount": 1
  },
  {
    "id": 1266,
    "nomCarte": "Birds of Paradise",
    "edition": "Revised",
    "langue": "English",
    "etat": "GD",
    "estimatedPrice": 15.49,
    "pricingModel": "standard_fallback_condition_ratio",
    "marketAnchorPrice": 18.37,
    "ratioUsed": 0.8431,
    "confidence": 35,
    "observationCount": 0
  },
  {
    "id": 1267,
    "nomCarte": "Birds of Paradise",
    "edition": "Revised",
    "langue": "English",
    "etat": "GD",
    "estimatedPrice": 15.49,
    "pricingModel": "standard_fallback_condition_ratio",
    "marketAnchorPrice": 18.37,
    "ratioUsed": 0.8431,
    "confidence": 35,
    "observationCount": 0
  },
  {
    "id": 1268,
    "nomCarte": "Black Vise",
    "edition": "Revised",
    "langue": "English",
    "etat": "EX",
    "estimatedPrice": 1.99,
    "pricingModel": "standard_fallback_condition_ratio",
    "marketAnchorPrice": 1.92,
    "ratioUsed": 1.0341,
    "confidence": 35,
    "observationCount": 0
  },
  {
    "id": 1269,
    "nomCarte": "Blue Elemental Blast",
    "edition": "Revised",
    "langue": "English",
    "etat": "EX",
    "estimatedPrice": 2.32,
    "pricingModel": "standard_fallback_condition_ratio",
    "marketAnchorPrice": 2.24,
    "ratioUsed": 1.0341,
    "confidence": 35,
    "observationCount": 0
  },
  {
    "id": 1270,
    "nomCarte": "Dark Ritual",
    "edition": "Revised",
    "langue": "English",
    "etat": "EX",
    "estimatedPrice": 2.18,
    "pricingModel": "standard_fallback_condition_ratio",
    "marketAnchorPrice": 2.11,
    "ratioUsed": 1.0341,
    "confidence": 35,
    "observationCount": 0
  },
  {
    "id": 1271,
    "nomCarte": "Dark Ritual",
    "edition": "Revised",
    "langue": "English",
    "etat": "EX",
    "estimatedPrice": 2.18,
    "pricingModel": "standard_fallback_condition_ratio",
    "marketAnchorPrice": 2.11,
    "ratioUsed": 1.0341,
    "confidence": 35,
    "observationCount": 0
  },
  {
    "id": 1272,
    "nomCarte": "Dark Ritual",
    "edition": "Revised",
    "langue": "English",
    "etat": "EX",
    "estimatedPrice": 2.18,
    "pricingModel": "standard_fallback_condition_ratio",
    "marketAnchorPrice": 2.11,
    "ratioUsed": 1.0341,
    "confidence": 35,
    "observationCount": 0
  },
  {
    "id": 1273,
    "nomCarte": "Dark Ritual",
    "edition": "Revised",
    "langue": "English",
    "etat": "NM",
    "estimatedPrice": 3.32,
    "pricingModel": "standard_fallback_condition_ratio",
    "marketAnchorPrice": 2.11,
    "ratioUsed": 1.5743,
    "confidence": 35,
    "observationCount": 0
  },
  {
    "id": 1274,
    "nomCarte": "Demonic Tutor",
    "edition": "Revised",
    "langue": "English",
    "etat": "NM",
    "estimatedPrice": 59.73,
    "pricingModel": "standard_fallback_condition_ratio",
    "marketAnchorPrice": 37.94,
    "ratioUsed": 1.5743,
    "confidence": 35,
    "observationCount": 0
  },
  {
    "id": 1275,
    "nomCarte": "Fork",
    "edition": "Revised",
    "langue": "English",
    "etat": "PO",
    "estimatedPrice": 14.47,
    "pricingModel": "standard_fallback_condition_ratio",
    "marketAnchorPrice": 20.05,
    "ratioUsed": 0.7215,
    "confidence": 35,
    "observationCount": 0
  },
  {
    "id": 1276,
    "nomCarte": "Hypnotic Specter",
    "edition": "Revised",
    "langue": "English",
    "etat": "EX",
    "estimatedPrice": 5.05,
    "pricingModel": "standard_fallback_condition_ratio",
    "marketAnchorPrice": 4.88,
    "ratioUsed": 1.0341,
    "confidence": 35,
    "observationCount": 0
  },
  {
    "id": 1277,
    "nomCarte": "Hypnotic Specter",
    "edition": "Revised",
    "langue": "English",
    "etat": "EX",
    "estimatedPrice": 5.05,
    "pricingModel": "standard_fallback_condition_ratio",
    "marketAnchorPrice": 4.88,
    "ratioUsed": 1.0341,
    "confidence": 35,
    "observationCount": 0
  },
  {
    "id": 1278,
    "nomCarte": "Nightmare",
    "edition": "Revised",
    "langue": "English",
    "etat": "PL",
    "estimatedPrice": 1.98,
    "pricingModel": "standard_fallback_condition_ratio",
    "marketAnchorPrice": 2.96,
    "ratioUsed": 0.6705,
    "confidence": 35,
    "observationCount": 0
  },
  {
    "id": 1279,
    "nomCarte": "Royal Assassin",
    "edition": "Revised",
    "langue": "English",
    "etat": "EX",
    "estimatedPrice": 6.74,
    "pricingModel": "standard_fallback_condition_ratio",
    "marketAnchorPrice": 6.52,
    "ratioUsed": 1.0341,
    "confidence": 35,
    "observationCount": 0
  },
  {
    "id": 1280,
    "nomCarte": "Sengir Vampire",
    "edition": "Revised",
    "langue": "English",
    "etat": "NM",
    "estimatedPrice": 2.24,
    "pricingModel": "standard_fallback_condition_ratio",
    "marketAnchorPrice": 1.42,
    "ratioUsed": 1.5743,
    "confidence": 35,
    "observationCount": 0
  },
  {
    "id": 1281,
    "nomCarte": "Sengir Vampire",
    "edition": "Revised",
    "langue": "English",
    "etat": "EX",
    "estimatedPrice": 1.47,
    "pricingModel": "standard_fallback_condition_ratio",
    "marketAnchorPrice": 1.42,
    "ratioUsed": 1.0341,
    "confidence": 35,
    "observationCount": 0
  },
  {
    "id": 1282,
    "nomCarte": "Taiga",
    "edition": "Revised",
    "langue": "English",
    "etat": "EX",
    "estimatedPrice": 265.92,
    "pricingModel": "standard_fallback_condition_ratio",
    "marketAnchorPrice": 257.15,
    "ratioUsed": 1.0341,
    "confidence": 35,
    "observationCount": 0
  },
  {
    "id": 1283,
    "nomCarte": "Verduran Enchantress",
    "edition": "Revised",
    "langue": "English",
    "etat": "EX",
    "estimatedPrice": 2,
    "pricingModel": "standard_observed_condition_ratio",
    "marketAnchorPrice": 2.52,
    "ratioUsed": 0.7937,
    "confidence": 63,
    "observationCount": 1
  },
  {
    "id": 1284,
    "nomCarte": "Will-o'-the-Wisp",
    "edition": "Revised",
    "langue": "English",
    "etat": "GD",
    "estimatedPrice": 2.07,
    "pricingModel": "standard_fallback_condition_ratio",
    "marketAnchorPrice": 2.46,
    "ratioUsed": 0.8431,
    "confidence": 35,
    "observationCount": 0
  },
  {
    "id": 1285,
    "nomCarte": "Niall Silvain",
    "edition": "The Dark",
    "langue": "English",
    "etat": "EX",
    "estimatedPrice": 2.6,
    "pricingModel": "standard_observed_condition_ratio",
    "marketAnchorPrice": 3.3,
    "ratioUsed": 0.7879,
    "confidence": 63,
    "observationCount": 1
  },
  {
    "id": 1286,
    "nomCarte": "Spitting Slug",
    "edition": "The Dark",
    "langue": "English",
    "etat": "EX",
    "estimatedPrice": 2.25,
    "pricingModel": "standard_observed_condition_ratio",
    "marketAnchorPrice": 3.63,
    "ratioUsed": 0.6198,
    "confidence": 63,
    "observationCount": 1
  },
  {
    "id": 1287,
    "nomCarte": "Wormwood Treefolk",
    "edition": "The Dark",
    "langue": "English",
    "etat": "EX",
    "estimatedPrice": 4.64,
    "pricingModel": "standard_fallback_condition_ratio",
    "marketAnchorPrice": 4.49,
    "ratioUsed": 1.0341,
    "confidence": 35,
    "observationCount": 0
  },
  {
    "id": 1288,
    "nomCarte": "Llanowar Elves",
    "edition": "Unlimited",
    "langue": "English",
    "etat": "NM",
    "estimatedPrice": 16.77,
    "pricingModel": "standard_fallback_condition_ratio",
    "marketAnchorPrice": 10.65,
    "ratioUsed": 1.5743,
    "confidence": 35,
    "observationCount": 0
  },
  {
    "id": 1289,
    "nomCarte": "Sinkhole",
    "edition": "Unlimited",
    "langue": "English",
    "etat": "EX",
    "estimatedPrice": 19.65,
    "pricingModel": "standard_fallback_condition_ratio",
    "marketAnchorPrice": 19,
    "ratioUsed": 1.0341,
    "confidence": 35,
    "observationCount": 0
  },
  {
    "id": 1290,
    "nomCarte": "Sinkhole",
    "edition": "Unlimited",
    "langue": "English",
    "etat": "GD",
    "estimatedPrice": 16.02,
    "pricingModel": "standard_fallback_condition_ratio",
    "marketAnchorPrice": 19,
    "ratioUsed": 0.8431,
    "confidence": 35,
    "observationCount": 0
  },
  {
    "id": 1291,
    "nomCarte": "Sinkhole",
    "edition": "Unlimited",
    "langue": "English",
    "etat": "GD",
    "estimatedPrice": 16.02,
    "pricingModel": "standard_fallback_condition_ratio",
    "marketAnchorPrice": 19,
    "ratioUsed": 0.8431,
    "confidence": 35,
    "observationCount": 0
  },
  {
    "id": 1292,
    "nomCarte": "Sinkhole",
    "edition": "Unlimited",
    "langue": "English",
    "etat": "EX",
    "estimatedPrice": 19.65,
    "pricingModel": "standard_fallback_condition_ratio",
    "marketAnchorPrice": 19,
    "ratioUsed": 1.0341,
    "confidence": 35,
    "observationCount": 0
  },
  {
    "id": 1293,
    "nomCarte": "Sinkhole",
    "edition": "Unlimited",
    "langue": "English",
    "etat": "EX",
    "estimatedPrice": 19.65,
    "pricingModel": "standard_fallback_condition_ratio",
    "marketAnchorPrice": 19,
    "ratioUsed": 1.0341,
    "confidence": 35,
    "observationCount": 0
  },
  {
    "id": 1294,
    "nomCarte": "Manabarbs",
    "edition": "Foreign White Bordered",
    "langue": "French",
    "etat": "EX",
    "estimatedPrice": 4.57,
    "pricingModel": "standard_fallback_condition_ratio",
    "marketAnchorPrice": 4.42,
    "ratioUsed": 1.0341,
    "confidence": 35,
    "observationCount": 0
  },
  {
    "id": 1295,
    "nomCarte": "Fireball",
    "edition": "Foreign Black Bordered",
    "langue": "French",
    "etat": "EX",
    "estimatedPrice": 0.19,
    "pricingModel": "standard_observed_condition_ratio",
    "marketAnchorPrice": 0.51,
    "ratioUsed": 0.3725,
    "confidence": 63,
    "observationCount": 1
  },
  {
    "id": 1296,
    "nomCarte": "Mishra's Factory",
    "edition": "Renaissance",
    "langue": "French",
    "etat": "EX",
    "estimatedPrice": 9,
    "pricingModel": "standard_observed_condition_ratio",
    "marketAnchorPrice": 9.83,
    "ratioUsed": 0.9156,
    "confidence": 63,
    "observationCount": 1
  },
  {
    "id": 1297,
    "nomCarte": "Goblin King",
    "edition": "Revised",
    "langue": "English",
    "etat": "NM",
    "estimatedPrice": 7.81,
    "pricingModel": "standard_fallback_condition_ratio",
    "marketAnchorPrice": 4.96,
    "ratioUsed": 1.5743,
    "confidence": 35,
    "observationCount": 0
  },
  {
    "id": 1298,
    "nomCarte": "Hammerheim",
    "edition": "Legends",
    "langue": "English",
    "etat": "EX",
    "estimatedPrice": 16.11,
    "pricingModel": "standard_fallback_condition_ratio",
    "marketAnchorPrice": 15.58,
    "ratioUsed": 1.0341,
    "confidence": 35,
    "observationCount": 0
  },
  {
    "id": 1299,
    "nomCarte": "Wheel of Fortune",
    "edition": "Foreign White Bordered",
    "langue": "French",
    "etat": "NM",
    "estimatedPrice": 410.07,
    "pricingModel": "standard_fallback_condition_ratio",
    "marketAnchorPrice": 260.48,
    "ratioUsed": 1.5743,
    "confidence": 35,
    "observationCount": 0
  },
  {
    "id": 1300,
    "nomCarte": "Fireball",
    "edition": "Foreign Black Bordered",
    "langue": "French",
    "etat": "EX",
    "estimatedPrice": 0.19,
    "pricingModel": "standard_observed_condition_ratio",
    "marketAnchorPrice": 0.51,
    "ratioUsed": 0.3725,
    "confidence": 63,
    "observationCount": 1
  },
  {
    "id": 1301,
    "nomCarte": "Disintegrate",
    "edition": "Unlimited",
    "langue": "English",
    "etat": "GD",
    "estimatedPrice": 1.46,
    "pricingModel": "standard_fallback_condition_ratio",
    "marketAnchorPrice": 1.73,
    "ratioUsed": 0.8431,
    "confidence": 35,
    "observationCount": 0
  },
  {
    "id": 1302,
    "nomCarte": "Detonate",
    "edition": "Antiquities",
    "langue": "English",
    "etat": "EX",
    "estimatedPrice": 4.2,
    "pricingModel": "standard_fallback_condition_ratio",
    "marketAnchorPrice": 4.06,
    "ratioUsed": 1.0341,
    "confidence": 35,
    "observationCount": 0
  },
  {
    "id": 1303,
    "nomCarte": "Manabarbs",
    "edition": "Foreign White Bordered",
    "langue": "French",
    "etat": "GD",
    "estimatedPrice": 3.73,
    "pricingModel": "standard_fallback_condition_ratio",
    "marketAnchorPrice": 4.42,
    "ratioUsed": 0.8431,
    "confidence": 35,
    "observationCount": 0
  },
  {
    "id": 1304,
    "nomCarte": "Ankh of Mishra",
    "edition": "Revised",
    "langue": "English",
    "etat": "EX",
    "estimatedPrice": 6.95,
    "pricingModel": "standard_observed_condition_ratio",
    "marketAnchorPrice": 7.55,
    "ratioUsed": 0.9205,
    "confidence": 63,
    "observationCount": 1
  },
  {
    "id": 1305,
    "nomCarte": "Red Elemental Blast",
    "edition": "Foreign White Bordered",
    "langue": "French",
    "etat": "EX",
    "estimatedPrice": 4,
    "pricingModel": "standard_observed_condition_ratio",
    "marketAnchorPrice": 5.89,
    "ratioUsed": 0.6791,
    "confidence": 63,
    "observationCount": 1
  },
  {
    "id": 1306,
    "nomCarte": "Nevinyrral's Disk",
    "edition": "Foreign White Bordered",
    "langue": "French",
    "etat": "EX",
    "estimatedPrice": 4,
    "pricingModel": "standard_observed_condition_ratio",
    "marketAnchorPrice": 5.94,
    "ratioUsed": 0.6734,
    "confidence": 63,
    "observationCount": 1
  },
  {
    "id": 1307,
    "nomCarte": "Blood Moon",
    "edition": "Chronicles",
    "langue": "English",
    "etat": "EX",
    "estimatedPrice": 7.99,
    "pricingModel": "standard_fallback_condition_ratio",
    "marketAnchorPrice": 7.73,
    "ratioUsed": 1.0341,
    "confidence": 35,
    "observationCount": 0
  },
  {
    "id": 1308,
    "nomCarte": "Blood Moon",
    "edition": "Chronicles",
    "langue": "English",
    "etat": "EX",
    "estimatedPrice": 7.99,
    "pricingModel": "standard_fallback_condition_ratio",
    "marketAnchorPrice": 7.73,
    "ratioUsed": 1.0341,
    "confidence": 35,
    "observationCount": 0
  },
  {
    "id": 1309,
    "nomCarte": "Red Elemental Blast",
    "edition": "Fourth Edition",
    "langue": "French",
    "etat": "NM",
    "estimatedPrice": 8.33,
    "pricingModel": "standard_fallback_condition_ratio",
    "marketAnchorPrice": 5.29,
    "ratioUsed": 1.5743,
    "confidence": 35,
    "observationCount": 0
  },
  {
    "id": 1310,
    "nomCarte": "Red Elemental Blast",
    "edition": "Fourth Edition",
    "langue": "French",
    "etat": "EX",
    "estimatedPrice": 5.47,
    "pricingModel": "standard_fallback_condition_ratio",
    "marketAnchorPrice": 5.29,
    "ratioUsed": 1.0341,
    "confidence": 35,
    "observationCount": 0
  },
  {
    "id": 1311,
    "nomCarte": "Ball Lightning",
    "edition": "Renaissance",
    "langue": "French",
    "etat": "GD",
    "estimatedPrice": 5.67,
    "pricingModel": "standard_fallback_condition_ratio",
    "marketAnchorPrice": 6.72,
    "ratioUsed": 0.8431,
    "confidence": 35,
    "observationCount": 0
  },
  {
    "id": 1312,
    "nomCarte": "Fork",
    "edition": "Revised",
    "langue": "English",
    "etat": "EX",
    "estimatedPrice": 20.73,
    "pricingModel": "standard_fallback_condition_ratio",
    "marketAnchorPrice": 20.05,
    "ratioUsed": 1.0341,
    "confidence": 35,
    "observationCount": 0
  },
  {
    "id": 1313,
    "nomCarte": "Ball Lightning",
    "edition": "Renaissance",
    "langue": "French",
    "etat": "EX",
    "estimatedPrice": 6.95,
    "pricingModel": "standard_fallback_condition_ratio",
    "marketAnchorPrice": 6.72,
    "ratioUsed": 1.0341,
    "confidence": 35,
    "observationCount": 0
  },
  {
    "id": 1314,
    "nomCarte": "Lightning Bolt",
    "edition": "Foreign Black Bordered",
    "langue": "French",
    "etat": "EX",
    "estimatedPrice": 13.2,
    "pricingModel": "standard_fallback_condition_ratio",
    "marketAnchorPrice": 12.76,
    "ratioUsed": 1.0341,
    "confidence": 35,
    "observationCount": 0
  },
  {
    "id": 1315,
    "nomCarte": "Lightning Bolt",
    "edition": "Foreign Black Bordered",
    "langue": "French",
    "etat": "EX",
    "estimatedPrice": 13.2,
    "pricingModel": "standard_fallback_condition_ratio",
    "marketAnchorPrice": 12.76,
    "ratioUsed": 1.0341,
    "confidence": 35,
    "observationCount": 0
  },
  {
    "id": 1316,
    "nomCarte": "Lightning Bolt",
    "edition": "Foreign Black Bordered",
    "langue": "French",
    "etat": "EX",
    "estimatedPrice": 13.2,
    "pricingModel": "standard_fallback_condition_ratio",
    "marketAnchorPrice": 12.76,
    "ratioUsed": 1.0341,
    "confidence": 35,
    "observationCount": 0
  },
  {
    "id": 1317,
    "nomCarte": "Lightning Bolt",
    "edition": "Foreign Black Bordered",
    "langue": "French",
    "etat": "EX",
    "estimatedPrice": 13.2,
    "pricingModel": "standard_fallback_condition_ratio",
    "marketAnchorPrice": 12.76,
    "ratioUsed": 1.0341,
    "confidence": 35,
    "observationCount": 0
  },
  {
    "id": 1318,
    "nomCarte": "Chain Lightning",
    "edition": "Legends",
    "langue": "English",
    "etat": "EX",
    "estimatedPrice": 9.88,
    "pricingModel": "standard_fallback_condition_ratio",
    "marketAnchorPrice": 9.55,
    "ratioUsed": 1.0341,
    "confidence": 35,
    "observationCount": 0
  },
  {
    "id": 1319,
    "nomCarte": "Strip Mine",
    "edition": "Renaissance",
    "langue": "French",
    "etat": "EX",
    "estimatedPrice": 5.49,
    "pricingModel": "standard_observed_condition_ratio",
    "marketAnchorPrice": 6.28,
    "ratioUsed": 0.8742,
    "confidence": 63,
    "observationCount": 1
  },
  {
    "id": 1320,
    "nomCarte": "Ball Lightning",
    "edition": "Renaissance",
    "langue": "French",
    "etat": "EX",
    "estimatedPrice": 6.95,
    "pricingModel": "standard_fallback_condition_ratio",
    "marketAnchorPrice": 6.72,
    "ratioUsed": 1.0341,
    "confidence": 35,
    "observationCount": 0
  },
  {
    "id": 1321,
    "nomCarte": "Fork",
    "edition": "Revised",
    "langue": "English",
    "etat": "NM",
    "estimatedPrice": 31.56,
    "pricingModel": "standard_fallback_condition_ratio",
    "marketAnchorPrice": 20.05,
    "ratioUsed": 1.5743,
    "confidence": 35,
    "observationCount": 0
  },
  {
    "id": 1322,
    "nomCarte": "Chain Lightning",
    "edition": "Legends",
    "langue": "English",
    "etat": "EX",
    "estimatedPrice": 9.88,
    "pricingModel": "standard_fallback_condition_ratio",
    "marketAnchorPrice": 9.55,
    "ratioUsed": 1.0341,
    "confidence": 35,
    "observationCount": 0
  },
  {
    "id": 1323,
    "nomCarte": "Chain Lightning",
    "edition": "Legends",
    "langue": "English",
    "etat": "GD",
    "estimatedPrice": 8.05,
    "pricingModel": "standard_fallback_condition_ratio",
    "marketAnchorPrice": 9.55,
    "ratioUsed": 0.8431,
    "confidence": 35,
    "observationCount": 0
  },
  {
    "id": 1324,
    "nomCarte": "Chain Lightning",
    "edition": "Legends",
    "langue": "English",
    "etat": "GD",
    "estimatedPrice": 8.05,
    "pricingModel": "standard_fallback_condition_ratio",
    "marketAnchorPrice": 9.55,
    "ratioUsed": 0.8431,
    "confidence": 35,
    "observationCount": 0
  },
  {
    "id": 1325,
    "nomCarte": "Force of Will",
    "edition": "Alliances",
    "langue": "French",
    "etat": "EX",
    "estimatedPrice": 49.89,
    "pricingModel": "standard_observed_condition_ratio",
    "marketAnchorPrice": 48.67,
    "ratioUsed": 1.0251,
    "confidence": 63,
    "observationCount": 1
  },
  {
    "id": 1326,
    "nomCarte": "Elvish Spirit Guide",
    "edition": "Alliances",
    "langue": "French",
    "etat": "NM",
    "estimatedPrice": 2.5,
    "pricingModel": "standard_observed_condition_ratio",
    "marketAnchorPrice": 3.1,
    "ratioUsed": 0.8065,
    "confidence": 63,
    "observationCount": 1
  },
  {
    "id": 1327,
    "nomCarte": "Kaysa",
    "edition": "Alliances",
    "langue": "French",
    "etat": "NM",
    "estimatedPrice": 4.31,
    "pricingModel": "standard_fallback_condition_ratio",
    "marketAnchorPrice": 2.74,
    "ratioUsed": 1.5743,
    "confidence": 35,
    "observationCount": 0
  },
  {
    "id": 1328,
    "nomCarte": "Lim-Dûl's Vault",
    "edition": "Alliances",
    "langue": "French",
    "etat": "EX",
    "estimatedPrice": 4.05,
    "pricingModel": "standard_fallback_condition_ratio",
    "marketAnchorPrice": 3.92,
    "ratioUsed": 1.0341,
    "confidence": 35,
    "observationCount": 0
  },
  {
    "id": 1329,
    "nomCarte": "Heart of Yavimaya",
    "edition": "Alliances",
    "langue": "French",
    "etat": "EX",
    "estimatedPrice": 1.49,
    "pricingModel": "standard_fallback_condition_ratio",
    "marketAnchorPrice": 1.44,
    "ratioUsed": 1.0341,
    "confidence": 35,
    "observationCount": 0
  },
  {
    "id": 1330,
    "nomCarte": "Lake of the Dead",
    "edition": "Alliances",
    "langue": "French",
    "etat": "EX",
    "estimatedPrice": 69.95,
    "pricingModel": "standard_observed_condition_ratio",
    "marketAnchorPrice": 81.66,
    "ratioUsed": 0.8566,
    "confidence": 63,
    "observationCount": 1
  },
  {
    "id": 1331,
    "nomCarte": "Army of Allah (V.1)",
    "edition": "Arabian Nights",
    "langue": "English",
    "etat": "NM",
    "estimatedPrice": 37.34,
    "pricingModel": "standard_fallback_condition_ratio",
    "marketAnchorPrice": 23.72,
    "ratioUsed": 1.5743,
    "confidence": 35,
    "observationCount": 0
  },
  {
    "id": 1332,
    "nomCarte": "Disenchant",
    "edition": "Foreign Black Bordered",
    "langue": "French",
    "etat": "EX",
    "estimatedPrice": 0.95,
    "pricingModel": "standard_fallback_condition_ratio",
    "marketAnchorPrice": 0.92,
    "ratioUsed": 1.0341,
    "confidence": 35,
    "observationCount": 0
  },
  {
    "id": 1333,
    "nomCarte": "Jihad",
    "edition": "Arabian Nights",
    "langue": "English",
    "etat": "EX",
    "estimatedPrice": 300,
    "pricingModel": "manual_observed",
    "marketAnchorPrice": null,
    "ratioUsed": null,
    "confidence": 60,
    "observationCount": 1
  },
  {
    "id": 1334,
    "nomCarte": "Karakas",
    "edition": "Legends",
    "langue": "English",
    "etat": "EX",
    "estimatedPrice": 35.7,
    "pricingModel": "standard_observed_condition_ratio",
    "marketAnchorPrice": 51.74,
    "ratioUsed": 0.69,
    "confidence": 63,
    "observationCount": 1
  },
  {
    "id": 1335,
    "nomCarte": "Sol Ring",
    "edition": "Revised",
    "langue": "English",
    "etat": "EX",
    "estimatedPrice": 12,
    "pricingModel": "standard_observed_condition_ratio",
    "marketAnchorPrice": 9.44,
    "ratioUsed": 1.2712,
    "confidence": 63,
    "observationCount": 1
  },
  {
    "id": 1336,
    "nomCarte": "Dust to Dust",
    "edition": "The Dark",
    "langue": "English",
    "etat": "GD",
    "estimatedPrice": 10,
    "pricingModel": "standard_observed_condition_ratio",
    "marketAnchorPrice": 12.52,
    "ratioUsed": 0.7987,
    "confidence": 63,
    "observationCount": 1
  },
  {
    "id": 1337,
    "nomCarte": "Dust to Dust",
    "edition": "The Dark",
    "langue": "English",
    "etat": "GD",
    "estimatedPrice": 10,
    "pricingModel": "standard_observed_condition_ratio",
    "marketAnchorPrice": 12.52,
    "ratioUsed": 0.7987,
    "confidence": 63,
    "observationCount": 1
  },
  {
    "id": 1338,
    "nomCarte": "Aeolipile",
    "edition": "Fallen Empires",
    "langue": "English",
    "etat": "EX",
    "estimatedPrice": 3.26,
    "pricingModel": "standard_fallback_condition_ratio",
    "marketAnchorPrice": 3.15,
    "ratioUsed": 1.0341,
    "confidence": 35,
    "observationCount": 0
  },
  {
    "id": 1339,
    "nomCarte": "Crusade",
    "edition": "Foreign White Bordered",
    "langue": "French",
    "etat": "GD",
    "estimatedPrice": 2.5,
    "pricingModel": "manual_observed",
    "marketAnchorPrice": null,
    "ratioUsed": null,
    "confidence": 60,
    "observationCount": 1
  },
  {
    "id": 1340,
    "nomCarte": "Aeolipile",
    "edition": "Fallen Empires",
    "langue": "English",
    "etat": "NM",
    "estimatedPrice": 4.96,
    "pricingModel": "standard_fallback_condition_ratio",
    "marketAnchorPrice": 3.15,
    "ratioUsed": 1.5743,
    "confidence": 35,
    "observationCount": 0
  },
  {
    "id": 1341,
    "nomCarte": "Swords to Plowshares",
    "edition": "Foreign White Bordered",
    "langue": "French",
    "etat": "GD",
    "estimatedPrice": 2.25,
    "pricingModel": "standard_observed_condition_ratio",
    "marketAnchorPrice": 6.19,
    "ratioUsed": 0.3635,
    "confidence": 63,
    "observationCount": 1
  },
  {
    "id": 1342,
    "nomCarte": "Preacher",
    "edition": "The Dark",
    "langue": "English",
    "etat": "EX",
    "estimatedPrice": 33.45,
    "pricingModel": "standard_fallback_condition_ratio",
    "marketAnchorPrice": 32.35,
    "ratioUsed": 1.0341,
    "confidence": 35,
    "observationCount": 0
  },
  {
    "id": 1343,
    "nomCarte": "Swords to Plowshares",
    "edition": "Foreign White Bordered",
    "langue": "French",
    "etat": "GD",
    "estimatedPrice": 2.25,
    "pricingModel": "standard_observed_condition_ratio",
    "marketAnchorPrice": 6.19,
    "ratioUsed": 0.3635,
    "confidence": 63,
    "observationCount": 1
  },
  {
    "id": 1344,
    "nomCarte": "Swords to Plowshares",
    "edition": "Revised",
    "langue": "English",
    "etat": "EX",
    "estimatedPrice": 6.4,
    "pricingModel": "standard_fallback_condition_ratio",
    "marketAnchorPrice": 6.19,
    "ratioUsed": 1.0341,
    "confidence": 35,
    "observationCount": 0
  },
  {
    "id": 1345,
    "nomCarte": "Holy Light",
    "edition": "The Dark",
    "langue": "English",
    "etat": "EX",
    "estimatedPrice": 5.29,
    "pricingModel": "standard_fallback_condition_ratio",
    "marketAnchorPrice": 5.12,
    "ratioUsed": 1.0341,
    "confidence": 35,
    "observationCount": 0
  },
  {
    "id": 1346,
    "nomCarte": "Witch Hunter",
    "edition": "The Dark",
    "langue": "English",
    "etat": "GD",
    "estimatedPrice": 3.86,
    "pricingModel": "standard_fallback_condition_ratio",
    "marketAnchorPrice": 4.58,
    "ratioUsed": 0.8431,
    "confidence": 35,
    "observationCount": 0
  },
  {
    "id": 1347,
    "nomCarte": "Crusade",
    "edition": "Foreign White Bordered",
    "langue": "French",
    "etat": "EX",
    "estimatedPrice": 7.98,
    "pricingModel": "manual_observed",
    "marketAnchorPrice": null,
    "ratioUsed": null,
    "confidence": 60,
    "observationCount": 1
  },
  {
    "id": 1348,
    "nomCarte": "Serra Angel",
    "edition": "Revised",
    "langue": "English",
    "etat": "EX",
    "estimatedPrice": 2.47,
    "pricingModel": "standard_fallback_condition_ratio",
    "marketAnchorPrice": 2.39,
    "ratioUsed": 1.0341,
    "confidence": 35,
    "observationCount": 0
  },
  {
    "id": 1349,
    "nomCarte": "Savannah Lions",
    "edition": "Revised",
    "langue": "English",
    "etat": "EX",
    "estimatedPrice": 5.68,
    "pricingModel": "standard_observed_condition_ratio",
    "marketAnchorPrice": 6.48,
    "ratioUsed": 0.8765,
    "confidence": 63,
    "observationCount": 1
  },
  {
    "id": 1350,
    "nomCarte": "Savannah Lions",
    "edition": "Revised",
    "langue": "English",
    "etat": "EX",
    "estimatedPrice": 5.68,
    "pricingModel": "standard_observed_condition_ratio",
    "marketAnchorPrice": 6.48,
    "ratioUsed": 0.8765,
    "confidence": 63,
    "observationCount": 1
  },
  {
    "id": 1351,
    "nomCarte": "Mishra's Factory",
    "edition": "Renaissance",
    "langue": "French",
    "etat": "EX",
    "estimatedPrice": 9,
    "pricingModel": "standard_observed_condition_ratio",
    "marketAnchorPrice": 9.83,
    "ratioUsed": 0.9156,
    "confidence": 63,
    "observationCount": 1
  },
  {
    "id": 1352,
    "nomCarte": "Armageddon",
    "edition": "Foreign White Bordered",
    "langue": "French",
    "etat": "EX",
    "estimatedPrice": 13.33,
    "pricingModel": "standard_fallback_condition_ratio",
    "marketAnchorPrice": 12.89,
    "ratioUsed": 1.0341,
    "confidence": 35,
    "observationCount": 0
  },
  {
    "id": 1353,
    "nomCarte": "Strip Mine",
    "edition": "Renaissance",
    "langue": "French",
    "etat": "EX",
    "estimatedPrice": 5.49,
    "pricingModel": "standard_observed_condition_ratio",
    "marketAnchorPrice": 6.28,
    "ratioUsed": 0.8742,
    "confidence": 63,
    "observationCount": 1
  },
  {
    "id": 1354,
    "nomCarte": "Land Tax",
    "edition": "Renaissance",
    "langue": "French",
    "etat": "NM",
    "estimatedPrice": 14.5,
    "pricingModel": "standard_observed_condition_ratio",
    "marketAnchorPrice": 15.2,
    "ratioUsed": 0.9539,
    "confidence": 71,
    "observationCount": 2
  },
  {
    "id": 1355,
    "nomCarte": "Armageddon",
    "edition": "Revised",
    "langue": "English",
    "etat": "EX",
    "estimatedPrice": 10,
    "pricingModel": "standard_observed_condition_ratio",
    "marketAnchorPrice": 12.89,
    "ratioUsed": 0.7758,
    "confidence": 63,
    "observationCount": 1
  },
  {
    "id": 1356,
    "nomCarte": "Greater Realm of Preservation",
    "edition": "Legends",
    "langue": "English",
    "etat": "EX",
    "estimatedPrice": 3.59,
    "pricingModel": "standard_observed_condition_ratio",
    "marketAnchorPrice": 4.09,
    "ratioUsed": 0.8778,
    "confidence": 63,
    "observationCount": 1
  },
  {
    "id": 1357,
    "nomCarte": "Crusade",
    "edition": "Fourth Edition",
    "langue": "French",
    "etat": "NM",
    "estimatedPrice": 0,
    "pricingModel": "standard_fallback_condition_ratio",
    "marketAnchorPrice": 0,
    "ratioUsed": 1.5743,
    "confidence": 0,
    "observationCount": 0
  },
  {
    "id": 1358,
    "nomCarte": "Disenchant",
    "edition": "Foreign Black Bordered",
    "langue": "French",
    "etat": "EX",
    "estimatedPrice": 0.95,
    "pricingModel": "standard_fallback_condition_ratio",
    "marketAnchorPrice": 0.92,
    "ratioUsed": 1.0341,
    "confidence": 35,
    "observationCount": 0
  },
  {
    "id": 1359,
    "nomCarte": "Holy Light",
    "edition": "The Dark",
    "langue": "English",
    "etat": "NM",
    "estimatedPrice": 8.06,
    "pricingModel": "standard_fallback_condition_ratio",
    "marketAnchorPrice": 5.12,
    "ratioUsed": 1.5743,
    "confidence": 35,
    "observationCount": 0
  },
  {
    "id": 1360,
    "nomCarte": "Savannah Lions",
    "edition": "Revised",
    "langue": "English",
    "etat": "EX",
    "estimatedPrice": 5.68,
    "pricingModel": "standard_observed_condition_ratio",
    "marketAnchorPrice": 6.48,
    "ratioUsed": 0.8765,
    "confidence": 63,
    "observationCount": 1
  },
  {
    "id": 1361,
    "nomCarte": "Serra Angel",
    "edition": "Revised",
    "langue": "English",
    "etat": "EX",
    "estimatedPrice": 2.47,
    "pricingModel": "standard_fallback_condition_ratio",
    "marketAnchorPrice": 2.39,
    "ratioUsed": 1.0341,
    "confidence": 35,
    "observationCount": 0
  },
  {
    "id": 1362,
    "nomCarte": "Disenchant",
    "edition": "Foreign Black Bordered",
    "langue": "French",
    "etat": "EX",
    "estimatedPrice": 0.95,
    "pricingModel": "standard_fallback_condition_ratio",
    "marketAnchorPrice": 0.92,
    "ratioUsed": 1.0341,
    "confidence": 35,
    "observationCount": 0
  },
  {
    "id": 1363,
    "nomCarte": "Thunder Spirit",
    "edition": "Legends",
    "langue": "English",
    "etat": "EX",
    "estimatedPrice": 115,
    "pricingModel": "standard_observed_condition_ratio",
    "marketAnchorPrice": 114.85,
    "ratioUsed": 1.0013,
    "confidence": 63,
    "observationCount": 1
  },
  {
    "id": 1364,
    "nomCarte": "Thunder Spirit",
    "edition": "Legends",
    "langue": "English",
    "etat": "EX",
    "estimatedPrice": 115,
    "pricingModel": "standard_observed_condition_ratio",
    "marketAnchorPrice": 114.85,
    "ratioUsed": 1.0013,
    "confidence": 63,
    "observationCount": 1
  },
  {
    "id": 1365,
    "nomCarte": "Divine Offering",
    "edition": "Legends",
    "langue": "English",
    "etat": "EX",
    "estimatedPrice": 1.57,
    "pricingModel": "standard_fallback_condition_ratio",
    "marketAnchorPrice": 1.52,
    "ratioUsed": 1.0341,
    "confidence": 35,
    "observationCount": 0
  },
  {
    "id": 1366,
    "nomCarte": "Balance",
    "edition": "Fourth Edition",
    "langue": "French",
    "etat": "EX",
    "estimatedPrice": 2,
    "pricingModel": "standard_observed_condition_ratio",
    "marketAnchorPrice": 2.46,
    "ratioUsed": 0.813,
    "confidence": 71,
    "observationCount": 2
  },
  {
    "id": 1367,
    "nomCarte": "Swords to Plowshares",
    "edition": "Revised",
    "langue": "English",
    "etat": "EX",
    "estimatedPrice": 6.4,
    "pricingModel": "standard_fallback_condition_ratio",
    "marketAnchorPrice": 6.19,
    "ratioUsed": 1.0341,
    "confidence": 35,
    "observationCount": 0
  },
  {
    "id": 1368,
    "nomCarte": "Disenchant",
    "edition": "Foreign Black Bordered",
    "langue": "French",
    "etat": "EX",
    "estimatedPrice": 0.95,
    "pricingModel": "standard_fallback_condition_ratio",
    "marketAnchorPrice": 0.92,
    "ratioUsed": 1.0341,
    "confidence": 35,
    "observationCount": 0
  },
  {
    "id": 1369,
    "nomCarte": "Savannah Lions",
    "edition": "Revised",
    "langue": "English",
    "etat": "EX",
    "estimatedPrice": 5.68,
    "pricingModel": "standard_observed_condition_ratio",
    "marketAnchorPrice": 6.48,
    "ratioUsed": 0.8765,
    "confidence": 63,
    "observationCount": 1
  },
  {
    "id": 1370,
    "nomCarte": "Crusade",
    "edition": "Foreign White Bordered",
    "langue": "French",
    "etat": "EX",
    "estimatedPrice": 7.98,
    "pricingModel": "manual_observed",
    "marketAnchorPrice": null,
    "ratioUsed": null,
    "confidence": 60,
    "observationCount": 1
  },
  {
    "id": 1371,
    "nomCarte": "Jayemdae Tome",
    "edition": "Revised",
    "langue": "English",
    "etat": "GD",
    "estimatedPrice": 2.3,
    "pricingModel": "standard_fallback_condition_ratio",
    "marketAnchorPrice": 2.73,
    "ratioUsed": 0.8431,
    "confidence": 35,
    "observationCount": 0
  },
  {
    "id": 1372,
    "nomCarte": "Serra Angel",
    "edition": "Revised",
    "langue": "English",
    "etat": "GD",
    "estimatedPrice": 2.02,
    "pricingModel": "standard_fallback_condition_ratio",
    "marketAnchorPrice": 2.39,
    "ratioUsed": 0.8431,
    "confidence": 35,
    "observationCount": 0
  },
  {
    "id": 1373,
    "nomCarte": "Su-Chi",
    "edition": "Antiquities",
    "langue": "English",
    "etat": "NM",
    "estimatedPrice": 102.61,
    "pricingModel": "standard_observed_condition_ratio",
    "marketAnchorPrice": 94.19,
    "ratioUsed": 1.0894,
    "confidence": 63,
    "observationCount": 1
  },
  {
    "id": 1374,
    "nomCarte": "Pendelhaven",
    "edition": "Legends",
    "langue": "English",
    "etat": "GD",
    "estimatedPrice": 17.37,
    "pricingModel": "standard_fallback_condition_ratio",
    "marketAnchorPrice": 20.6,
    "ratioUsed": 0.8431,
    "confidence": 35,
    "observationCount": 0
  },
  {
    "id": 1375,
    "nomCarte": "Sylvan Library",
    "edition": "Renaissance",
    "langue": "French",
    "etat": "EX",
    "estimatedPrice": 27.72,
    "pricingModel": "standard_observed_condition_ratio",
    "marketAnchorPrice": 40.91,
    "ratioUsed": 0.6776,
    "confidence": 63,
    "observationCount": 1
  },
  {
    "id": 1376,
    "nomCarte": "Berserk",
    "edition": "Unlimited",
    "langue": "English",
    "etat": "NM",
    "estimatedPrice": 129,
    "pricingModel": "standard_observed_condition_ratio",
    "marketAnchorPrice": 101.58,
    "ratioUsed": 1.2699,
    "confidence": 63,
    "observationCount": 1
  },
  {
    "id": 1377,
    "nomCarte": "Llanowar Elves",
    "edition": "Foreign Black Bordered",
    "langue": "French",
    "etat": "EX",
    "estimatedPrice": 2.95,
    "pricingModel": "standard_observed_condition_ratio",
    "marketAnchorPrice": 4.27,
    "ratioUsed": 0.6909,
    "confidence": 63,
    "observationCount": 1
  },
  {
    "id": 1378,
    "nomCarte": "Ice Storm",
    "edition": "Unlimited",
    "langue": "English",
    "etat": "GD",
    "estimatedPrice": 55.56,
    "pricingModel": "standard_fallback_condition_ratio",
    "marketAnchorPrice": 65.9,
    "ratioUsed": 0.8431,
    "confidence": 35,
    "observationCount": 0
  },
  {
    "id": 1379,
    "nomCarte": "Berserk",
    "edition": "Unlimited",
    "langue": "English",
    "etat": "EX",
    "estimatedPrice": 88,
    "pricingModel": "standard_observed_condition_ratio",
    "marketAnchorPrice": 101.58,
    "ratioUsed": 0.8663,
    "confidence": 63,
    "observationCount": 1
  },
  {
    "id": 1380,
    "nomCarte": "Llanowar Elves",
    "edition": "Foreign Black Bordered",
    "langue": "French",
    "etat": "EX",
    "estimatedPrice": 2.95,
    "pricingModel": "standard_observed_condition_ratio",
    "marketAnchorPrice": 4.27,
    "ratioUsed": 0.6909,
    "confidence": 63,
    "observationCount": 1
  },
  {
    "id": 1381,
    "nomCarte": "Su-Chi",
    "edition": "Antiquities",
    "langue": "English",
    "etat": "EX",
    "estimatedPrice": 92,
    "pricingModel": "standard_observed_condition_ratio",
    "marketAnchorPrice": 94.19,
    "ratioUsed": 0.9767,
    "confidence": 63,
    "observationCount": 1
  },
  {
    "id": 1382,
    "nomCarte": "Berserk",
    "edition": "Unlimited",
    "langue": "English",
    "etat": "GD",
    "estimatedPrice": 90,
    "pricingModel": "standard_observed_condition_ratio",
    "marketAnchorPrice": 101.58,
    "ratioUsed": 0.886,
    "confidence": 63,
    "observationCount": 1
  },
  {
    "id": 1383,
    "nomCarte": "Llanowar Elves",
    "edition": "Foreign Black Bordered",
    "langue": "French",
    "etat": "EX",
    "estimatedPrice": 2.95,
    "pricingModel": "standard_observed_condition_ratio",
    "marketAnchorPrice": 4.27,
    "ratioUsed": 0.6909,
    "confidence": 63,
    "observationCount": 1
  },
  {
    "id": 1384,
    "nomCarte": "Pendelhaven",
    "edition": "Legends",
    "langue": "English",
    "etat": "GD",
    "estimatedPrice": 17.37,
    "pricingModel": "standard_fallback_condition_ratio",
    "marketAnchorPrice": 20.6,
    "ratioUsed": 0.8431,
    "confidence": 35,
    "observationCount": 0
  },
  {
    "id": 1385,
    "nomCarte": "Sylvan Library",
    "edition": "Renaissance",
    "langue": "French",
    "etat": "EX",
    "estimatedPrice": 27.72,
    "pricingModel": "standard_observed_condition_ratio",
    "marketAnchorPrice": 40.91,
    "ratioUsed": 0.6776,
    "confidence": 63,
    "observationCount": 1
  },
  {
    "id": 1386,
    "nomCarte": "Sol Ring",
    "edition": "Foreign Black Bordered",
    "langue": "French",
    "etat": "EX",
    "estimatedPrice": 30,
    "pricingModel": "standard_observed_condition_ratio",
    "marketAnchorPrice": 35.52,
    "ratioUsed": 0.8446,
    "confidence": 71,
    "observationCount": 2
  },
  {
    "id": 1387,
    "nomCarte": "Mishra's Factory",
    "edition": "Renaissance",
    "langue": "French",
    "etat": "EX",
    "estimatedPrice": 9,
    "pricingModel": "standard_observed_condition_ratio",
    "marketAnchorPrice": 9.83,
    "ratioUsed": 0.9156,
    "confidence": 63,
    "observationCount": 1
  },
  {
    "id": 1388,
    "nomCarte": "Ice Storm",
    "edition": "Unlimited",
    "langue": "English",
    "etat": "GD",
    "estimatedPrice": 55.56,
    "pricingModel": "standard_fallback_condition_ratio",
    "marketAnchorPrice": 65.9,
    "ratioUsed": 0.8431,
    "confidence": 35,
    "observationCount": 0
  },
  {
    "id": 1389,
    "nomCarte": "Force of Nature",
    "edition": "Foreign Black Bordered",
    "langue": "French",
    "etat": "EX",
    "estimatedPrice": 24.9,
    "pricingModel": "standard_observed_condition_ratio",
    "marketAnchorPrice": 9.32,
    "ratioUsed": 2.6717,
    "confidence": 63,
    "observationCount": 1
  },
  {
    "id": 1390,
    "nomCarte": "Strip Mine (V.3)",
    "edition": "Antiquities",
    "langue": "English",
    "etat": "NM",
    "estimatedPrice": 36.9,
    "pricingModel": "standard_fallback_condition_ratio",
    "marketAnchorPrice": 23.44,
    "ratioUsed": 1.5743,
    "confidence": 35,
    "observationCount": 0
  },
  {
    "id": 1391,
    "nomCarte": "Ice Storm",
    "edition": "Unlimited",
    "langue": "English",
    "etat": "EX",
    "estimatedPrice": 68.15,
    "pricingModel": "standard_fallback_condition_ratio",
    "marketAnchorPrice": 65.9,
    "ratioUsed": 1.0341,
    "confidence": 35,
    "observationCount": 0
  },
  {
    "id": 1392,
    "nomCarte": "Llanowar Elves",
    "edition": "Foreign Black Bordered",
    "langue": "French",
    "etat": "EX",
    "estimatedPrice": 2.95,
    "pricingModel": "standard_observed_condition_ratio",
    "marketAnchorPrice": 4.27,
    "ratioUsed": 0.6909,
    "confidence": 63,
    "observationCount": 1
  },
  {
    "id": 1393,
    "nomCarte": "Ice Storm",
    "edition": "Unlimited",
    "langue": "English",
    "etat": "EX",
    "estimatedPrice": 68.15,
    "pricingModel": "standard_fallback_condition_ratio",
    "marketAnchorPrice": 65.9,
    "ratioUsed": 1.0341,
    "confidence": 35,
    "observationCount": 0
  },
  {
    "id": 1394,
    "nomCarte": "Regrowth",
    "edition": "Foreign Black Bordered",
    "langue": "French",
    "etat": "EX",
    "estimatedPrice": 2.5,
    "pricingModel": "standard_observed_condition_ratio",
    "marketAnchorPrice": 1.97,
    "ratioUsed": 1.269,
    "confidence": 63,
    "observationCount": 1
  },
  {
    "id": 1395,
    "nomCarte": "Pendelhaven",
    "edition": "Legends",
    "langue": "English",
    "etat": "EX",
    "estimatedPrice": 21.3,
    "pricingModel": "standard_fallback_condition_ratio",
    "marketAnchorPrice": 20.6,
    "ratioUsed": 1.0341,
    "confidence": 35,
    "observationCount": 0
  },
  {
    "id": 1396,
    "nomCarte": "Berserk",
    "edition": "Unlimited",
    "langue": "English",
    "etat": "EX",
    "estimatedPrice": 88,
    "pricingModel": "standard_observed_condition_ratio",
    "marketAnchorPrice": 101.58,
    "ratioUsed": 0.8663,
    "confidence": 63,
    "observationCount": 1
  },
  {
    "id": 1397,
    "nomCarte": "Force of Nature",
    "edition": "Foreign Black Bordered",
    "langue": "French",
    "etat": "EX",
    "estimatedPrice": 24.9,
    "pricingModel": "standard_observed_condition_ratio",
    "marketAnchorPrice": 9.32,
    "ratioUsed": 2.6717,
    "confidence": 63,
    "observationCount": 1
  },
  {
    "id": 1398,
    "nomCarte": "Crumble",
    "edition": "Antiquities",
    "langue": "English",
    "etat": "EX",
    "estimatedPrice": 4.56,
    "pricingModel": "standard_fallback_condition_ratio",
    "marketAnchorPrice": 4.41,
    "ratioUsed": 1.0341,
    "confidence": 35,
    "observationCount": 0
  },
  {
    "id": 1399,
    "nomCarte": "Crumble",
    "edition": "Antiquities",
    "langue": "English",
    "etat": "EX",
    "estimatedPrice": 4.56,
    "pricingModel": "standard_fallback_condition_ratio",
    "marketAnchorPrice": 4.41,
    "ratioUsed": 1.0341,
    "confidence": 35,
    "observationCount": 0
  },
  {
    "id": 1400,
    "nomCarte": "Crumble",
    "edition": "Antiquities",
    "langue": "English",
    "etat": "NM",
    "estimatedPrice": 6.94,
    "pricingModel": "standard_fallback_condition_ratio",
    "marketAnchorPrice": 4.41,
    "ratioUsed": 1.5743,
    "confidence": 35,
    "observationCount": 0
  },
  {
    "id": 1401,
    "nomCarte": "Crumble",
    "edition": "Antiquities",
    "langue": "English",
    "etat": "NM",
    "estimatedPrice": 6.94,
    "pricingModel": "standard_fallback_condition_ratio",
    "marketAnchorPrice": 4.41,
    "ratioUsed": 1.5743,
    "confidence": 35,
    "observationCount": 0
  },
  {
    "id": 1402,
    "nomCarte": "Argothian Pixies",
    "edition": "Antiquities",
    "langue": "English",
    "etat": "NM",
    "estimatedPrice": 2.94,
    "pricingModel": "standard_fallback_condition_ratio",
    "marketAnchorPrice": 1.87,
    "ratioUsed": 1.5743,
    "confidence": 35,
    "observationCount": 0
  },
  {
    "id": 1403,
    "nomCarte": "Argothian Pixies",
    "edition": "Antiquities",
    "langue": "English",
    "etat": "EX",
    "estimatedPrice": 1.93,
    "pricingModel": "standard_fallback_condition_ratio",
    "marketAnchorPrice": 1.87,
    "ratioUsed": 1.0341,
    "confidence": 35,
    "observationCount": 0
  },
  {
    "id": 1404,
    "nomCarte": "Argothian Pixies",
    "edition": "Antiquities",
    "langue": "English",
    "etat": "NM",
    "estimatedPrice": 2.94,
    "pricingModel": "standard_fallback_condition_ratio",
    "marketAnchorPrice": 1.87,
    "ratioUsed": 1.5743,
    "confidence": 35,
    "observationCount": 0
  },
  {
    "id": 1405,
    "nomCarte": "Argothian Pixies",
    "edition": "Antiquities",
    "langue": "English",
    "etat": "EX",
    "estimatedPrice": 1.93,
    "pricingModel": "standard_fallback_condition_ratio",
    "marketAnchorPrice": 1.87,
    "ratioUsed": 1.0341,
    "confidence": 35,
    "observationCount": 0
  },
  {
    "id": 1406,
    "nomCarte": "Psionic Blast",
    "edition": "Unlimited",
    "langue": "English",
    "etat": "EX",
    "estimatedPrice": 63.24,
    "pricingModel": "standard_fallback_condition_ratio",
    "marketAnchorPrice": 61.15,
    "ratioUsed": 1.0341,
    "confidence": 35,
    "observationCount": 0
  },
  {
    "id": 1407,
    "nomCarte": "Psionic Blast",
    "edition": "Unlimited",
    "langue": "English",
    "etat": "EX",
    "estimatedPrice": 63.24,
    "pricingModel": "standard_fallback_condition_ratio",
    "marketAnchorPrice": 61.15,
    "ratioUsed": 1.0341,
    "confidence": 35,
    "observationCount": 0
  },
  {
    "id": 1408,
    "nomCarte": "Serendib Efreet",
    "edition": "Foreign White Bordered",
    "langue": "French",
    "etat": "GD",
    "estimatedPrice": 4.24,
    "pricingModel": "standard_fallback_condition_ratio",
    "marketAnchorPrice": 5.03,
    "ratioUsed": 0.8431,
    "confidence": 35,
    "observationCount": 0
  },
  {
    "id": 1409,
    "nomCarte": "Flying Men",
    "edition": "Arabian Nights",
    "langue": "English",
    "etat": "EX",
    "estimatedPrice": 10,
    "pricingModel": "standard_observed_condition_ratio",
    "marketAnchorPrice": 10.42,
    "ratioUsed": 0.9597,
    "confidence": 63,
    "observationCount": 1
  },
  {
    "id": 1410,
    "nomCarte": "Flying Men",
    "edition": "Arabian Nights",
    "langue": "English",
    "etat": "EX",
    "estimatedPrice": 10,
    "pricingModel": "standard_observed_condition_ratio",
    "marketAnchorPrice": 10.42,
    "ratioUsed": 0.9597,
    "confidence": 63,
    "observationCount": 1
  },
  {
    "id": 1411,
    "nomCarte": "Blue Elemental Blast",
    "edition": "Foreign White Bordered",
    "langue": "French",
    "etat": "NM",
    "estimatedPrice": 3.53,
    "pricingModel": "standard_fallback_condition_ratio",
    "marketAnchorPrice": 2.24,
    "ratioUsed": 1.5743,
    "confidence": 35,
    "observationCount": 0
  },
  {
    "id": 1412,
    "nomCarte": "Blue Elemental Blast",
    "edition": "Foreign White Bordered",
    "langue": "French",
    "etat": "NM",
    "estimatedPrice": 3.53,
    "pricingModel": "standard_fallback_condition_ratio",
    "marketAnchorPrice": 2.24,
    "ratioUsed": 1.5743,
    "confidence": 35,
    "observationCount": 0
  },
  {
    "id": 1413,
    "nomCarte": "Blue Elemental Blast",
    "edition": "Foreign White Bordered",
    "langue": "French",
    "etat": "NM",
    "estimatedPrice": 3.53,
    "pricingModel": "standard_fallback_condition_ratio",
    "marketAnchorPrice": 2.24,
    "ratioUsed": 1.5743,
    "confidence": 35,
    "observationCount": 0
  },
  {
    "id": 1414,
    "nomCarte": "Strip Mine",
    "edition": "Renaissance",
    "langue": "French",
    "etat": "EX",
    "estimatedPrice": 5.49,
    "pricingModel": "standard_observed_condition_ratio",
    "marketAnchorPrice": 6.28,
    "ratioUsed": 0.8742,
    "confidence": 63,
    "observationCount": 1
  },
  {
    "id": 1415,
    "nomCarte": "Braingeyser",
    "edition": "Foreign White Bordered",
    "langue": "French",
    "etat": "EX",
    "estimatedPrice": 11.51,
    "pricingModel": "standard_fallback_condition_ratio",
    "marketAnchorPrice": 11.13,
    "ratioUsed": 1.0341,
    "confidence": 35,
    "observationCount": 0
  },
  {
    "id": 1416,
    "nomCarte": "Lord of Atlantis",
    "edition": "Foreign White Bordered",
    "langue": "French",
    "etat": "EX",
    "estimatedPrice": 7.51,
    "pricingModel": "standard_fallback_condition_ratio",
    "marketAnchorPrice": 7.26,
    "ratioUsed": 1.0341,
    "confidence": 35,
    "observationCount": 0
  },
  {
    "id": 1417,
    "nomCarte": "Lord of Atlantis",
    "edition": "Foreign White Bordered",
    "langue": "French",
    "etat": "EX",
    "estimatedPrice": 7.51,
    "pricingModel": "standard_fallback_condition_ratio",
    "marketAnchorPrice": 7.26,
    "ratioUsed": 1.0341,
    "confidence": 35,
    "observationCount": 0
  },
  {
    "id": 1418,
    "nomCarte": "Tolaria",
    "edition": "Legends",
    "langue": "English",
    "etat": "EX",
    "estimatedPrice": 8.8,
    "pricingModel": "standard_fallback_condition_ratio",
    "marketAnchorPrice": 8.51,
    "ratioUsed": 1.0341,
    "confidence": 35,
    "observationCount": 0
  },
  {
    "id": 1419,
    "nomCarte": "Boomerang",
    "edition": "Legends",
    "langue": "English",
    "etat": "EX",
    "estimatedPrice": 2.68,
    "pricingModel": "standard_fallback_condition_ratio",
    "marketAnchorPrice": 2.59,
    "ratioUsed": 1.0341,
    "confidence": 35,
    "observationCount": 0
  },
  {
    "id": 1420,
    "nomCarte": "Boomerang",
    "edition": "Legends",
    "langue": "English",
    "etat": "EX",
    "estimatedPrice": 2.68,
    "pricingModel": "standard_fallback_condition_ratio",
    "marketAnchorPrice": 2.59,
    "ratioUsed": 1.0341,
    "confidence": 35,
    "observationCount": 0
  },
  {
    "id": 1421,
    "nomCarte": "Blue Elemental Blast",
    "edition": "Foreign White Bordered",
    "langue": "French",
    "etat": "NM",
    "estimatedPrice": 3.53,
    "pricingModel": "standard_fallback_condition_ratio",
    "marketAnchorPrice": 2.24,
    "ratioUsed": 1.5743,
    "confidence": 35,
    "observationCount": 0
  },
  {
    "id": 1422,
    "nomCarte": "Flying Men",
    "edition": "Arabian Nights",
    "langue": "English",
    "etat": "EX",
    "estimatedPrice": 10,
    "pricingModel": "standard_observed_condition_ratio",
    "marketAnchorPrice": 10.42,
    "ratioUsed": 0.9597,
    "confidence": 63,
    "observationCount": 1
  },
  {
    "id": 1423,
    "nomCarte": "Serendib Efreet",
    "edition": "Foreign White Bordered",
    "langue": "French",
    "etat": "EX",
    "estimatedPrice": 5.2,
    "pricingModel": "standard_fallback_condition_ratio",
    "marketAnchorPrice": 5.03,
    "ratioUsed": 1.0341,
    "confidence": 35,
    "observationCount": 0
  },
  {
    "id": 1424,
    "nomCarte": "Mishra's Factory",
    "edition": "Renaissance",
    "langue": "French",
    "etat": "EX",
    "estimatedPrice": 9,
    "pricingModel": "standard_observed_condition_ratio",
    "marketAnchorPrice": 9.83,
    "ratioUsed": 0.9156,
    "confidence": 63,
    "observationCount": 1
  },
  {
    "id": 1425,
    "nomCarte": "Clone",
    "edition": "Foreign White Bordered",
    "langue": "French",
    "etat": "EX",
    "estimatedPrice": 0.2,
    "pricingModel": "standard_observed_condition_ratio",
    "marketAnchorPrice": 0.98,
    "ratioUsed": 0.2041,
    "confidence": 63,
    "observationCount": 1
  },
  {
    "id": 1426,
    "nomCarte": "Psionic Blast",
    "edition": "Unlimited",
    "langue": "English",
    "etat": "EX",
    "estimatedPrice": 63.24,
    "pricingModel": "standard_fallback_condition_ratio",
    "marketAnchorPrice": 61.15,
    "ratioUsed": 1.0341,
    "confidence": 35,
    "observationCount": 0
  },
  {
    "id": 1427,
    "nomCarte": "Svyelunite Temple",
    "edition": "Fallen Empires",
    "langue": "English",
    "etat": "EX",
    "estimatedPrice": 2.09,
    "pricingModel": "standard_fallback_condition_ratio",
    "marketAnchorPrice": 2.02,
    "ratioUsed": 1.0341,
    "confidence": 35,
    "observationCount": 0
  },
  {
    "id": 1428,
    "nomCarte": "Psionic Blast",
    "edition": "Unlimited",
    "langue": "English",
    "etat": "NM",
    "estimatedPrice": 96.27,
    "pricingModel": "standard_fallback_condition_ratio",
    "marketAnchorPrice": 61.15,
    "ratioUsed": 1.5743,
    "confidence": 35,
    "observationCount": 0
  },
  {
    "id": 1429,
    "nomCarte": "Flying Men",
    "edition": "Arabian Nights",
    "langue": "English",
    "etat": "EX",
    "estimatedPrice": 10,
    "pricingModel": "standard_observed_condition_ratio",
    "marketAnchorPrice": 10.42,
    "ratioUsed": 0.9597,
    "confidence": 63,
    "observationCount": 1
  },
  {
    "id": 1430,
    "nomCarte": "Tolaria",
    "edition": "Legends",
    "langue": "English",
    "etat": "EX",
    "estimatedPrice": 8.8,
    "pricingModel": "standard_fallback_condition_ratio",
    "marketAnchorPrice": 8.51,
    "ratioUsed": 1.0341,
    "confidence": 35,
    "observationCount": 0
  },
  {
    "id": 1431,
    "nomCarte": "Unstable Mutation",
    "edition": "Arabian Nights",
    "langue": "English",
    "etat": "EX",
    "estimatedPrice": 3.76,
    "pricingModel": "standard_fallback_condition_ratio",
    "marketAnchorPrice": 3.64,
    "ratioUsed": 1.0341,
    "confidence": 35,
    "observationCount": 0
  },
  {
    "id": 1432,
    "nomCarte": "Unstable Mutation",
    "edition": "Arabian Nights",
    "langue": "English",
    "etat": "EX",
    "estimatedPrice": 3.76,
    "pricingModel": "standard_fallback_condition_ratio",
    "marketAnchorPrice": 3.64,
    "ratioUsed": 1.0341,
    "confidence": 35,
    "observationCount": 0
  },
  {
    "id": 1433,
    "nomCarte": "Mahamoti Djinn",
    "edition": "Revised",
    "langue": "English",
    "etat": "NM",
    "estimatedPrice": 3.64,
    "pricingModel": "standard_fallback_condition_ratio",
    "marketAnchorPrice": 2.31,
    "ratioUsed": 1.5743,
    "confidence": 35,
    "observationCount": 0
  },
  {
    "id": 1434,
    "nomCarte": "Counterspell",
    "edition": "Revised",
    "langue": "English",
    "etat": "NM",
    "estimatedPrice": 5.45,
    "pricingModel": "standard_fallback_condition_ratio",
    "marketAnchorPrice": 3.46,
    "ratioUsed": 1.5743,
    "confidence": 35,
    "observationCount": 0
  },
  {
    "id": 1435,
    "nomCarte": "Unstable Mutation",
    "edition": "Arabian Nights",
    "langue": "English",
    "etat": "EX",
    "estimatedPrice": 3.76,
    "pricingModel": "standard_fallback_condition_ratio",
    "marketAnchorPrice": 3.64,
    "ratioUsed": 1.0341,
    "confidence": 35,
    "observationCount": 0
  },
  {
    "id": 1436,
    "nomCarte": "Serendib Efreet",
    "edition": "Foreign White Bordered",
    "langue": "French",
    "etat": "EX",
    "estimatedPrice": 5.2,
    "pricingModel": "standard_fallback_condition_ratio",
    "marketAnchorPrice": 5.03,
    "ratioUsed": 1.0341,
    "confidence": 35,
    "observationCount": 0
  },
  {
    "id": 1437,
    "nomCarte": "Serendib Djinn",
    "edition": "Arabian Nights",
    "langue": "French",
    "etat": "EX",
    "estimatedPrice": 135.91,
    "pricingModel": "standard_fallback_condition_ratio",
    "marketAnchorPrice": 131.43,
    "ratioUsed": 1.0341,
    "confidence": 35,
    "observationCount": 0
  },
  {
    "id": 1438,
    "nomCarte": "Svyelunite Temple",
    "edition": "Fallen Empires",
    "langue": "English",
    "etat": "EX",
    "estimatedPrice": 2.09,
    "pricingModel": "standard_fallback_condition_ratio",
    "marketAnchorPrice": 2.02,
    "ratioUsed": 1.0341,
    "confidence": 35,
    "observationCount": 0
  },
  {
    "id": 1439,
    "nomCarte": "Lord of Atlantis",
    "edition": "Foreign White Bordered",
    "langue": "French",
    "etat": "GD",
    "estimatedPrice": 6.12,
    "pricingModel": "standard_fallback_condition_ratio",
    "marketAnchorPrice": 7.26,
    "ratioUsed": 0.8431,
    "confidence": 35,
    "observationCount": 0
  },
  {
    "id": 1440,
    "nomCarte": "Counterspell",
    "edition": "Foreign White Bordered",
    "langue": "French",
    "etat": "NM",
    "estimatedPrice": 5.45,
    "pricingModel": "standard_fallback_condition_ratio",
    "marketAnchorPrice": 3.46,
    "ratioUsed": 1.5743,
    "confidence": 35,
    "observationCount": 0
  },
  {
    "id": 1441,
    "nomCarte": "Counterspell",
    "edition": "Foreign White Bordered",
    "langue": "French",
    "etat": "NM",
    "estimatedPrice": 5.45,
    "pricingModel": "standard_fallback_condition_ratio",
    "marketAnchorPrice": 3.46,
    "ratioUsed": 1.5743,
    "confidence": 35,
    "observationCount": 0
  },
  {
    "id": 1442,
    "nomCarte": "Counterspell",
    "edition": "Foreign White Bordered",
    "langue": "French",
    "etat": "EX",
    "estimatedPrice": 3.58,
    "pricingModel": "standard_fallback_condition_ratio",
    "marketAnchorPrice": 3.46,
    "ratioUsed": 1.0341,
    "confidence": 35,
    "observationCount": 0
  },
  {
    "id": 1443,
    "nomCarte": "Unstable Mutation",
    "edition": "Arabian Nights",
    "langue": "English",
    "etat": "EX",
    "estimatedPrice": 3.76,
    "pricingModel": "standard_fallback_condition_ratio",
    "marketAnchorPrice": 3.64,
    "ratioUsed": 1.0341,
    "confidence": 35,
    "observationCount": 0
  },
  {
    "id": 1444,
    "nomCarte": "Serendib Efreet",
    "edition": "Foreign White Bordered",
    "langue": "French",
    "etat": "EX",
    "estimatedPrice": 5.2,
    "pricingModel": "standard_fallback_condition_ratio",
    "marketAnchorPrice": 5.03,
    "ratioUsed": 1.0341,
    "confidence": 35,
    "observationCount": 0
  },
  {
    "id": 1445,
    "nomCarte": "Sol Ring",
    "edition": "Foreign White Bordered",
    "langue": "French",
    "etat": "EX",
    "estimatedPrice": 9,
    "pricingModel": "standard_observed_condition_ratio",
    "marketAnchorPrice": 9.44,
    "ratioUsed": 0.9534,
    "confidence": 63,
    "observationCount": 1
  },
  {
    "id": 1446,
    "nomCarte": "Lord of Atlantis",
    "edition": "Foreign White Bordered",
    "langue": "French",
    "etat": "EX",
    "estimatedPrice": 7.51,
    "pricingModel": "standard_fallback_condition_ratio",
    "marketAnchorPrice": 7.26,
    "ratioUsed": 1.0341,
    "confidence": 35,
    "observationCount": 0
  }
]